[{"image_urls":["http:\/\/numismatics.org\/collectionimages\/19501999\/1952\/1952.123.111.rev.width350.jpg"],"from":-319,"to":-315,"title":"Silver Drachm of Alexander III, Sardes, 319 BC - 315 BC. 1952.123.111"},{"image_urls":["http:\/\/numismatics.org\/collectionimages\/20002049\/2002\/2002.46.508.rev.width350.jpg"],"from":-319,"to":-315,"title":"Silver Drachm, Sardes, 319 BC - 315 BC. 2002.46.508"},{"image_urls":["http:\/\/numismatics.org\/collectionimages\/19501999\/1950\/1950.153.1.rev.width350.jpg"],"from":-319,"to":-315,"title":"Silver 4 drachm (tetradrachm) of Alexander III, Sardes, 319 BC - 315 BC. 1950.153.1"},{"image_urls":["http:\/\/numismatics.org\/collectionimages\/19001949\/1944\/1944.100.31380.rev.width350.jpg"],"from":-319,"to":-315,"title":"Silver Drachm of Alexander III, Sardes, 319 BC - 315 BC. 1944.100.31380"},{"image_urls":["http:\/\/numismatics.org\/collectionimages\/19001949\/1944\/1944.100.31365.rev.width350.jpg"],"from":-319,"to":-315,"title":"Silver 4 drachm (tetradrachm) of Alexander III, Sardes, 319 BC - 315 BC. 1944.100.31365"},{"image_urls":["http:\/\/numismatics.org\/collectionimages\/19001949\/1944\/1944.100.31350.rev.width350.jpg"],"from":-319,"to":-315,"title":"Silver 4 drachm (tetradrachm) of Alexander III, Sardes, 319 BC - 315 BC. 1944.100.31350"},{"image_urls":["http:\/\/numismatics.org\/collectionimages\/19001949\/1944\/1944.100.31359.rev.width350.jpg"],"from":-319,"to":-315,"title":"Silver 4 drachm (tetradrachm) of Alexander III, Sardes, 319 BC - 315 BC. 1944.100.31359"},{"image_urls":["http:\/\/numismatics.org\/collectionimages\/19001949\/1944\/1944.100.31374.rev.width350.jpg"],"from":-319,"to":-315,"title":"Silver Drachm of Alexander III, Sardes, 319 BC - 315 BC. 1944.100.31374"},{"image_urls":["http:\/\/numismatics.org\/collectionimages\/19001949\/1944\/1944.100.31356.rev.width350.jpg"],"from":-319,"to":-315,"title":"Silver 4 drachm (tetradrachm) of Alexander III, Sardes, 319 BC - 315 BC. 1944.100.31356"},{"image_urls":["http:\/\/numismatics.org\/collectionimages\/19001949\/1944\/1944.100.31362.rev.width350.jpg"],"from":-319,"to":-315,"title":"Silver 4 drachm (tetradrachm) of Alexander III, Sardes, 319 BC - 315 BC. 1944.100.31362"},{"image_urls":["http:\/\/numismatics.org\/collectionimages\/19001949\/1944\/1944.100.31377.rev.width350.jpg"],"from":-319,"to":-315,"title":"Silver Drachm of Alexander III, Sardes, 319 BC - 315 BC. 1944.100.31377"},{"image_urls":["http:\/\/numismatics.org\/collectionimages\/19001949\/1944\/1944.100.31367.rev.width350.jpg"],"from":-319,"to":-315,"title":"Silver 4 drachm (tetradrachm) of Alexander III, Sardes, 319 BC - 315 BC. 1944.100.31367"},{"image_urls":["http:\/\/numismatics.org\/collectionimages\/19001949\/1944\/1944.100.31373.rev.width350.jpg"],"from":-319,"to":-315,"title":"Silver Drachm of Alexander III, Sardes, 319 BC - 315 BC. 1944.100.31373"},{"image_urls":["http:\/\/numismatics.org\/collectionimages\/19501999\/1952\/1952.123.110.rev.width350.jpg"],"from":-319,"to":-315,"title":"Silver Drachm of Alexander III, Sardes, 319 BC - 315 BC. 1952.123.110"},{"image_urls":["http:\/\/numismatics.org\/collectionimages\/19001949\/1944\/1944.100.31371.rev.width350.jpg"],"from":-319,"to":-315,"title":"Silver Drachm of Alexander III, Sardes, 319 BC - 315 BC. 1944.100.31371"},{"image_urls":["http:\/\/numismatics.org\/collectionimages\/19001949\/1944\/1944.100.31353.rev.width350.jpg"],"from":-319,"to":-315,"title":"Silver 4 drachm (tetradrachm) of Alexander III, Sardes, 319 BC - 315 BC. 1944.100.31353"},{"image_urls":["http:\/\/numismatics.org\/collectionimages\/19001949\/1944\/1944.100.31347.rev.width350.jpg"],"from":-319,"to":-315,"title":"Silver 4 drachm (tetradrachm) of Alexander III, Sardes, 319 BC - 315 BC. 1944.100.31347"},{"image_urls":["http:\/\/numismatics.org\/collectionimages\/19001949\/1944\/1944.100.31379.rev.width350.jpg"],"from":-319,"to":-315,"title":"Silver Drachm of Alexander III, Sardes, 319 BC - 315 BC. 1944.100.31379"},{"image_urls":["http:\/\/numismatics.org\/collectionimages\/19501999\/1952\/1952.45.6.rev.width350.jpg"],"from":-319,"to":-315,"title":"Silver 4 drachm (tetradrachm) of Alexander III, Sardes, 319 BC - 315 BC. 1952.45.6"},{"image_urls":["http:\/\/numismatics.org\/collectionimages\/19001949\/1944\/1944.100.31363.rev.width350.jpg"],"from":-319,"to":-315,"title":"Silver 4 drachm (tetradrachm) of Alexander III, Sardes, 319 BC - 315 BC. 1944.100.31363"},{"image_urls":["http:\/\/numismatics.org\/collectionimages\/19001949\/1944\/1944.100.31355.rev.width350.jpg"],"from":-319,"to":-315,"title":"Silver 4 drachm (tetradrachm) of Alexander III, Sardes, 319 BC - 315 BC. 1944.100.31355"},{"image_urls":["http:\/\/numismatics.org\/collectionimages\/19001949\/1944\/1944.100.31361.rev.width350.jpg"],"from":-319,"to":-315,"title":"Silver 4 drachm (tetradrachm) of Alexander III, Sardes, 319 BC - 315 BC. 1944.100.31361"},{"image_urls":["http:\/\/numismatics.org\/collectionimages\/19001949\/1944\/1944.100.31378.rev.width350.jpg"],"from":-319,"to":-315,"title":"Silver Drachm of Alexander III, Sardes, 319 BC - 315 BC. 1944.100.31378"},{"image_urls":["http:\/\/numismatics.org\/collectionimages\/19001949\/1944\/1944.100.31345.rev.width350.jpg"],"from":-319,"to":-315,"title":"Silver 4 drachm (tetradrachm) of Alexander III, Sardes, 319 BC - 315 BC. 1944.100.31345"},{"image_urls":["http:\/\/numismatics.org\/collectionimages\/19001949\/1944\/1944.100.31364.rev.width350.jpg"],"from":-319,"to":-315,"title":"Silver 4 drachm (tetradrachm) of Alexander III, Sardes, 319 BC - 315 BC. 1944.100.31364"},{"image_urls":["http:\/\/numismatics.org\/collectionimages\/19001949\/1944\/1944.100.31370.rev.width350.jpg"],"from":-319,"to":-315,"title":"Silver Drachm of Alexander III, Sardes, 319 BC - 315 BC. 1944.100.31370"},{"image_urls":["http:\/\/numismatics.org\/collectionimages\/19001949\/1944\/1944.100.31352.rev.width350.jpg"],"from":-319,"to":-315,"title":"Silver 4 drachm (tetradrachm) of Alexander III, Sardes, 319 BC - 315 BC. 1944.100.31352"},{"image_urls":["http:\/\/numismatics.org\/collectionimages\/19001949\/1944\/1944.100.31349.rev.width350.jpg"],"from":-319,"to":-315,"title":"Silver 4 drachm (tetradrachm) of Alexander III, Sardes, 319 BC - 315 BC. 1944.100.31349"},{"image_urls":["http:\/\/numismatics.org\/collectionimages\/19001949\/1944\/1944.100.31382.rev.width350.jpg"],"from":-319,"to":-315,"title":"Bronze Unit of Alexander III, Sardes, 319 BC - 315 BC. 1944.100.31382"},{"image_urls":["http:\/\/numismatics.org\/collectionimages\/19001949\/1944\/1944.100.31376.rev.width350.jpg"],"from":-319,"to":-315,"title":"Silver Drachm of Alexander III, Sardes, 319 BC - 315 BC. 1944.100.31376"},{"image_urls":["http:\/\/numismatics.org\/collectionimages\/19001949\/1944\/1944.100.31358.rev.width350.jpg"],"from":-319,"to":-315,"title":"Silver 4 drachm (tetradrachm) of Alexander III, Sardes, 319 BC - 315 BC. 1944.100.31358"},{"image_urls":["http:\/\/numismatics.org\/collectionimages\/19001949\/1944\/1944.100.31368.rev.width350.jpg"],"from":-319,"to":-315,"title":"Silver Drachm of Alexander III, Sardes, 319 BC - 315 BC. 1944.100.31368"},{"image_urls":["http:\/\/numismatics.org\/collectionimages\/19001949\/1944\/1944.100.45117.rev.width350.jpg"],"from":-319,"to":-315,"title":"Silver 4 drachm (tetradrachm) of Alexander III, Sardes, 319 BC - 315 BC. 1944.100.45117"},{"image_urls":["http:\/\/numismatics.org\/collectionimages\/19501999\/1974\/1974.26.533.rev.width350.jpg"],"from":-319,"to":-315,"title":"Silver 4 drachm (tetradrachm) of Alexander III, Sardes, 319 BC - 315 BC. 1974.26.533"},{"image_urls":["http:\/\/numismatics.org\/collectionimages\/19001949\/1944\/1944.100.31381.rev.width350.jpg"],"from":-319,"to":-315,"title":"Silver Drachm of Alexander III, Sardes, 319 BC - 315 BC. 1944.100.31381"},{"image_urls":["http:\/\/numismatics.org\/collectionimages\/19001949\/1944\/1944.100.31360.rev.width350.jpg"],"from":-319,"to":-315,"title":"Silver 4 drachm (tetradrachm) of Alexander III, Sardes, 319 BC - 315 BC. 1944.100.31360"},{"image_urls":["http:\/\/numismatics.org\/collectionimages\/19001949\/1944\/1944.100.31375.rev.width350.jpg"],"from":-319,"to":-315,"title":"Silver Drachm of Alexander III, Sardes, 319 BC - 315 BC. 1944.100.31375"},{"image_urls":["http:\/\/numismatics.org\/collectionimages\/19001949\/1944\/1944.100.31351.rev.width350.jpg"],"from":-319,"to":-315,"title":"Silver 4 drachm (tetradrachm) of Alexander III, Sardes, 319 BC - 315 BC. 1944.100.31351"},{"image_urls":["http:\/\/numismatics.org\/collectionimages\/19001949\/1944\/1944.100.31348.rev.width350.jpg"],"from":-319,"to":-315,"title":"Silver 4 drachm (tetradrachm) of Alexander III, Sardes, 319 BC - 315 BC. 1944.100.31348"},{"image_urls":["http:\/\/numismatics.org\/collectionimages\/19001949\/1944\/1944.100.31357.rev.width350.jpg"],"from":-319,"to":-315,"title":"Silver 4 drachm (tetradrachm) of Alexander III, Sardes, 319 BC - 315 BC. 1944.100.31357"},{"image_urls":["http:\/\/numismatics.org\/collectionimages\/19001949\/1944\/1944.100.31372.rev.width350.jpg"],"from":-319,"to":-315,"title":"Silver Drachm of Alexander III, Sardes, 319 BC - 315 BC. 1944.100.31372"},{"image_urls":["http:\/\/numismatics.org\/collectionimages\/19001949\/1944\/1944.100.31366.rev.width350.jpg"],"from":-319,"to":-315,"title":"Silver 4 drachm (tetradrachm) of Alexander III, Sardes, 319 BC - 315 BC. 1944.100.31366"},{"image_urls":["http:\/\/numismatics.org\/collectionimages\/19001949\/1944\/1944.100.31354.rev.width350.jpg"],"from":-319,"to":-315,"title":"Silver 4 drachm (tetradrachm) of Alexander III, Sardes, 319 BC - 315 BC. 1944.100.31354"},{"image_urls":["http:\/\/numismatics.org\/collectionimages\/19001949\/1944\/1944.100.31369.rev.width350.jpg"],"from":-319,"to":-315,"title":"Silver Drachm of Alexander III, Sardes, 319 BC - 315 BC. 1944.100.31369"},{"image_urls":["http:\/\/numismatics.org\/collectionimages\/19001949\/1947\/1947.98.148.rev.width350.jpg"],"from":-319,"to":-315,"title":"Silver 4 drachm (tetradrachm) of Alexander III, Sardes, 319 BC - 315 BC. 1947.98.148"},{"image_urls":["http:\/\/numismatics.org\/collectionimages\/19501999\/1952\/1952.45.5.rev.width350.jpg"],"from":-319,"to":-315,"title":"Silver 4 drachm (tetradrachm) of Alexander III, Sardes, 319 BC - 315 BC. 1952.45.5"},{"image_urls":["http:\/\/numismatics.org\/collectionimages\/19001949\/1944\/1944.100.31346.rev.width350.jpg"],"from":-319,"to":-315,"title":"Silver 4 drachm (tetradrachm) of Alexander III, Sardes, 319 BC - 315 BC. 1944.100.31346"},{"image_urls":["https:\/\/finds.org.uk\/images\/pwalton\/greekstatermerg.jpg"],"from":-451,"to":-301,"title":"NCL-B2C487: A coin with an unrecorded\/uncertain issuer."},{"image_urls":["https:\/\/finds.org.uk\/images\/pwalton\/greekstatermerg.jpg"],"from":-451,"to":-301,"title":"NCL-B2C487: A coin with an unrecorded\/uncertain issuer."}]