{"image_urls":[https://finds.org.uk/images/stephaniesmith/SUSS-22FE03.jpg],"from":-1,"to":250,"title":"SUSS-22FE03: A coin issued by Uncertain - 1st-mid 3rd century"}{"image_urls":[https://finds.org.uk/images/abolton/WAW-9146A3.jpg],"from":-1,"to":250,"title":"WAW-9146A3: A coin issued by Uncertain - 1st-mid 3rd century"}{"image_urls":[https://finds.org.uk/images/abolton/WAW-E85235.jpg],"from":-1,"to":260,"title":"WAW-E85235: A coin issued by Uncertain - 1st-mid 3rd century"}{"image_urls":[https://finds.org.uk/images/mforeman/NLM24940.jpg],"from":-1,"to":200,"title":"NLM-29A533: A coin issued by Uncertain - 1st\/2nd Century AD"}{"image_urls":[https://finds.org.uk/images/abolton/WAW-916C64.jpg],"from":-1,"to":269,"title":"WAW-916C64: A coin issued by Uncertain - 1st-mid 3rd century"}{"image_urls":[https://finds.org.uk/images/abolton/WAW-E81E56.jpg],"from":-1,"to":260,"title":"WAW-E81E56: A coin issued by Uncertain - 1st-mid 3rd century"}{"image_urls":[https://finds.org.uk/images/karend1/KENT-759BB1.jpg],"from":-1,"to":250,"title":"KENT-759BB1: A coin issued by Uncertain - 1st-mid 3rd century"}{"image_urls":[https://finds.org.uk/images/abolton/WAW-63A374.jpg],"from":-1,"to":260,"title":"WAW-63A374: A coin issued by Uncertain - 1st-mid 3rd century"}{"image_urls":[https://finds.org.uk/images/stephaniesmith/SUSS-232DD3.jpg],"from":-1,"to":250,"title":"SUSS-232DD3: A coin issued by Uncertain - 1st-mid 3rd century"}{"image_urls":[https://finds.org.uk/images/abolton/WAW-E5C377.jpg],"from":-1,"to":250,"title":"WAW-E5C377: A coin issued by Uncertain - 1st-mid 3rd century"}{"image_urls":[https://finds.org.uk/images/dwilliams/11-236.jpg],"from":-1,"to":50,"title":"SUR-3E9E52: A coin issued by Verica"}{"image_urls":[https://finds.org.uk/images/abolton/WAW-6404F6.jpg],"from":-1,"to":260,"title":"WAW-6404F6: A coin with an unrecorded\/uncertain issuer."}{"image_urls":[https://finds.org.uk/images/dwilliams/B11-199.jpg],"from":-11,"to":20,"title":"SUR-EE6333: A coin issued by Eppillus"}{"image_urls":[https://finds.org.uk/images/jmoss/2DSCN2459.JPG],"from":-11,"to":40,"title":"BUC-D840B5: A coin issued by Cunobelin"}{"image_urls":[https://finds.org.uk/images/jplouviez/sf5293.jpg],"from":-11,"to":41,"title":"SF5293: A coin issued by Cunobelin"}{"image_urls":[https://finds.org.uk/images/jwatters/IA%20coin%2009%206%20-%202.jpg],"from":-11,"to":10,"title":"BH-483F60: A coin issued by RVES"}{"image_urls":[http://numismatics.org/collectionimages/20002049/2008/2008.1.7.rev.width350.jpg],"from":-11,"to":12,"title":"Bronze Coin, Byzantium, 11 BC - AD 12. 2008.1.7"}{"image_urls":[https://finds.org.uk/images/ellysg1/HAMP-40E637Denarius.jpg],"from":-118,"to":116,"title":"HAMP-40E637: A coin issued by Republic"}{"image_urls":[http://numismatics.org/collectionimages/19001949/1944/1944.100.70160.rev.width350.jpg],"from":-14,"to":100,"title":"Bronze Coin, Berytus, 14 BC - AD 100. 1944.100.70160"}{"image_urls":[http://numismatics.org/collectionimages/19001949/1944/1944.100.70159.rev.width350.jpg],"from":-14,"to":100,"title":"Bronze Coin, Berytus, 14 BC - AD 100. 1944.100.70159"}{"image_urls":[https://finds.org.uk/images/maritime/619.%20Gold%20Quarter%20Stater%20Y619.jpg],"from":-16,"to":10,"title":"BERK-0C37D5: A coin issued by Tasciovanus"}{"image_urls":[https://finds.org.uk/images/fbasford/IOW2007-1-537.JPG],"from":-16,"to":15,"title":"IOW-F52A23: A coin issued by Augustus"}{"image_urls":[http://numismatics.org/collectionimages/19001949/1944/1944.100.79594.rev.width350.jpg],"from":-17,"to":21,"title":"Bronze Coin, Leptis Magna, 17 BC - AD 21. 1944.100.79594"}{"image_urls":[http://numismatics.org/collectionimages/19001949/1944/1944.100.78841.rev.width350.jpg],"from":-2,"to":14,"title":"Silver Denarius of Augustus, Lugdunum, 2 BC - AD 14. 1944.100.78841"}{"image_urls":[https://finds.org.uk/images/abrown/LYM_SF-AC2416.jpg],"from":-201,"to":42,"title":"SF-AC2416: A coin issued by Republic"}{"image_urls":[https://finds.org.uk/images/abrown/LYM_SF-AC19D4.jpg],"from":-201,"to":42,"title":"SF-AC19D4: A coin issued by Republic"}{"image_urls":[https://finds.org.uk/images/abrown/LYM_SF-AC2FF8.jpg],"from":-201,"to":42,"title":"SF-AC2FF8: A coin issued by Republic"}{"image_urls":[https://finds.org.uk/images/abrown/WGN%20SF-5430B4.jpg],"from":-21,"to":10,"title":"SF-5430B4: A coin issued by Tasciovanus"}{"image_urls":[https://finds.org.uk/images/jwatters/IA%20coin%2009%206%20-%201b.jpg],"from":-21,"to":10,"title":"BH-4810D4: A coin issued by Tasciovanus"}{"image_urls":[https://finds.org.uk/images/jwatters/IA_coin_TLB2013_70%20copy.jpg],"from":-21,"to":10,"title":"BH-6E9216: A coin issued by Tasciovanus"}{"image_urls":[https://finds.org.uk/images/jwatters/Iron%20Age%20coin%2003%2098%20-%203a.jpg],"from":-21,"to":40,"title":"BH-225167: A coin issued by Tasciovanus"}{"image_urls":[https://finds.org.uk/images/jcassidy/NARC-01294Eb.jpg],"from":-21,"to":10,"title":"NARC-01294E: A coin issued by Tasciovanus"}{"image_urls":[https://finds.org.uk/images/jwatters/IA_coin_12_105_36a.jpg],"from":-21,"to":10,"title":"BH-6B1A00: A coin issued by Tasciovanus"}{"image_urls":[https://finds.org.uk/images/jwatters/IA_coin_13_13_10.jpg],"from":-21,"to":10,"title":"BH-24D0E6: A coin issued by Tasciovanus"}{"image_urls":[https://finds.org.uk/images/jwatters/IA%20coin%2009%20172%20-%204.jpg],"from":-21,"to":10,"title":"BH-64D297: A coin issued by Tasciovanus"}{"image_urls":[https://finds.org.uk/images/jwatters/IA%20coin%2010%2026%20-%2014.jpg],"from":-21,"to":10,"title":"BH-536458: A coin issued by Tasciovanus"}{"image_urls":[https://finds.org.uk/images/jwatters/IA%20coin%2009%206%20-%205a.jpg],"from":-21,"to":10,"title":"BH-48A1B2: A coin issued by Tasciovanus"}{"image_urls":[https://finds.org.uk/images/jwatters/IA%20coin%2010%2038%20-%206.jpg],"from":-21,"to":10,"title":"BH-590573: A coin issued by Tasciovanus"}{"image_urls":[https://finds.org.uk/images/arichardson/KENT3E4676a.jpg],"from":-21,"to":10,"title":"KENT-3E4676: A coin issued by Tasciovanus"}{"image_urls":[https://finds.org.uk/images/dwilliams/B15209.JPG],"from":-21,"to":10,"title":"SUR-63FEA3: A coin with an unrecorded\/uncertain issuer."}{"image_urls":[https://finds.org.uk/images/jwatters/Iron%20Age%20coin%200352%20-%203%20all.jpg],"from":-21,"to":10,"title":"BH-0CB952: A coin issued by Tasciovanus"}{"image_urls":[https://finds.org.uk/images/jwatters/IA_coin_13_13_7.jpg],"from":-21,"to":10,"title":"BH-250214: A coin issued by Tasciovanus"}{"image_urls":[https://finds.org.uk/images/hfowler/CAM-9C5696.jpg],"from":-21,"to":10,"title":"CAM-9C5696: A coin issued by Tasciovanus"}{"image_urls":[https://finds.org.uk/images/abyard/2012484b.JPG],"from":-21,"to":10,"title":"BERK-C6AB07: A coin issued by Tasciovanus"}{"image_urls":[https://finds.org.uk/images/jwatters/IA%20coin%2009%20170%20-%2010%20.jpg],"from":-21,"to":10,"title":"BH-28BA76: A coin issued by Tasciovanus"}{"image_urls":[https://finds.org.uk/images/jwatters/IA%20coin%2009%20180%20-%202.jpg],"from":-21,"to":10,"title":"BH-A96987: A coin issued by Tasciovanus"}{"image_urls":[https://finds.org.uk/images/jwatters/IA%20coin%2009%2014%20-%202a.jpg],"from":-21,"to":10,"title":"BH-ED9CD4: A coin issued by Tasciovanus"}{"image_urls":[https://finds.org.uk/images/jwatters/Iron%20Age%20coin%2004%2072%20-%201%20all.jpg],"from":-21,"to":10,"title":"BH-1ED132: A coin issued by Tasciovanus"}{"image_urls":[https://finds.org.uk/images/dwilliams/15879.JPG],"from":-21,"to":10,"title":"SUR-3F8899: A coin issued by Tasciovanus"}{"image_urls":[https://finds.org.uk/images/jwatters/IA_coin_14_83_5%20copy.jpg],"from":-21,"to":10,"title":"BH-296DED: A coin issued by Tasciovanus"}{"image_urls":[https://finds.org.uk/images/jwatters/IA_coin_14_153_1%20copy.jpg],"from":-21,"to":10,"title":"BH-A8D8F8: A coin issued by Tasciovanus"}{"image_urls":[https://finds.org.uk/images/rwebley/NARC-A70A90ironageunitobv.jpg],"from":-21,"to":10,"title":"NARC-A70A90: A coin issued by Tasciovanus"}{"image_urls":[https://finds.org.uk/images/jwatters/IA%20coin%2009%20159%20-%2028.jpg],"from":-21,"to":10,"title":"BH-B5B427: A coin issued by Tasciovanus"}{"image_urls":[https://finds.org.uk/images/jwatters/IA_coin_14_97_3.jpg],"from":-21,"to":10,"title":"BH-72A142: A coin issued by Tasciovanus"}{"image_urls":[https://finds.org.uk/images/jwatters/IA_coin_12_164_1.jpg],"from":-21,"to":10,"title":"BH-CB7F78: A coin issued by Tasciovanus"}{"image_urls":[https://finds.org.uk/images/dwilliams/B15611.JPG],"from":-21,"to":10,"title":"SUR-0DB9F9: A coin issued by Tincomarus"}{"image_urls":[https://finds.org.uk/images/lmclean/05D9D2%20Iron%20Age%20coin.jpg],"from":-21,"to":10,"title":"ESS-05D9D2: A coin issued by Tasciovanus"}{"image_urls":[https://finds.org.uk/images/jwatters/IA%20coin%2006%20126%20-%201.jpg],"from":-21,"to":10,"title":"BH-A2DC75: A coin issued by Tasciovanus"}{"image_urls":[https://finds.org.uk/images/jwatters/IA_coin_12_163_2.jpg],"from":-21,"to":10,"title":"BH-DFF5B6: A coin issued by Tasciovanus"}{"image_urls":[https://finds.org.uk/images/jwatters/Roman%20coin%2009%20174%20-%201.jpg],"from":-212,"to":100,"title":"BH-91A0C3: A coin issued by Republic"}{"image_urls":[http://numismatics.org/collectionimages/19001949/1944/1944.100.83911.rev.width350.jpg],"from":-214,"to":204,"title":"Bronze Coin, Ilerda, 214 BC - AD 204. 1944.100.83911"}{"image_urls":[https://finds.org.uk/images/abolton/WAW-B3C8A8.jpg],"from":-24,"to":260,"title":"WAW-B3C8A8: A coin issued by Uncertain - 1st-mid 3rd century"}{"image_urls":[https://finds.org.uk/images/preavill/HESH-B920B4.jpg],"from":-24,"to":260,"title":"HESH-B920B4: A coin issued by Uncertain - 1st-mid 3rd century"}{"image_urls":[https://finds.org.uk/images/abolton/WAW-648394.jpg],"from":-24,"to":269,"title":"WAW-648394: A coin issued by Uncertain - 1st-mid 3rd century"}{"image_urls":[https://finds.org.uk/images/abolton/WAW-54A5B3.jpg],"from":-24,"to":260,"title":"WAW-54A5B3: A coin issued by Uncertain - 1st-mid 3rd century"}{"image_urls":[https://finds.org.uk/images/abolton/WAW8AB9C8.jpg],"from":-24,"to":260,"title":"WAW-8AB9C8: A coin issued by Uncertain - 1st-mid 3rd century"}{"image_urls":[https://finds.org.uk/images/abolton/WAW-585077.jpg],"from":-24,"to":269,"title":"WAW-585077: A coin issued by Uncertain - 1st-mid 3rd century"}{"image_urls":[https://finds.org.uk/images/wakefield/SWYOR-2E6B64.jpg],"from":-24,"to":275,"title":"SWYOR-2E6B64: A coin with an unrecorded\/uncertain issuer."}{"image_urls":[https://finds.org.uk/images/abolton/WAW-5EF7D4.jpg],"from":-24,"to":269,"title":"WAW-5EF7D4: A coin issued by Uncertain - 1st-mid 3rd century"}{"image_urls":[https://finds.org.uk/images/abolton/WAW-CCCB4C.jpg],"from":-24,"to":269,"title":"WAW-CCCB4C: A coin issued by Uncertain - 1st-mid 3rd century"}{"image_urls":[https://finds.org.uk/images/eloisemarkwick/WAW-F18641.jpg],"from":-24,"to":269,"title":"WAW-F18641: A coin issued by Uncertain - 1st-mid 3rd century"}{"image_urls":[https://finds.org.uk/images/abolton/WAW-C2F634.jpg],"from":-24,"to":269,"title":"WAW-C2F634: A coin issued by Uncertain - 1st-mid 3rd century"}{"image_urls":[https://finds.org.uk/images/abolton/WAW8AD4EB.jpg],"from":-24,"to":260,"title":"WAW-8AD4EB: A coin issued by Uncertain - 1st-mid 3rd century"}{"image_urls":[https://finds.org.uk/images/abolton/WAW-97A976.jpg],"from":-24,"to":260,"title":"WAW-97A976: A coin issued by Uncertain - 1st-mid 3rd century"}{"image_urls":[https://finds.org.uk/images/preavill/HESH-B93AA7.jpg],"from":-24,"to":260,"title":"HESH-B93AA7: A coin issued by Uncertain - 1st-mid 3rd century"}{"image_urls":[https://finds.org.uk/images/abolton/WAW-5B8A37%20rename.jpg],"from":-24,"to":269,"title":"WAW-5B8A37: A coin issued by Uncertain - 1st-mid 3rd century"}{"image_urls":[https://finds.org.uk/images/abolton/WAW-B09632.jpg],"from":-24,"to":250,"title":"WAW-B09632: A coin issued by Uncertain - 1st-mid 3rd century"}{"image_urls":[https://finds.org.uk/images/preavill/HESH-B8A665.jpg],"from":-24,"to":369,"title":"HESH-B8A665: A coin issued by Uncertain - 1st-mid 3rd century"}{"image_urls":[https://finds.org.uk/images/abolton/WAW1C8B42.jpg],"from":-24,"to":250,"title":"WAW-1C8B42: A coin issued by Uncertain - 1st-mid 3rd century"}{"image_urls":[https://finds.org.uk/images/abolton/WAW-C2D4A7.jpg],"from":-24,"to":260,"title":"WAW-C2D4A7: A coin issued by Uncertain - 1st-mid 3rd century"}{"image_urls":[https://finds.org.uk/images/abolton/WAW-E3AA14.jpg],"from":-24,"to":260,"title":"WAW-E3AA14: A coin issued by Uncertain - 1st-mid 3rd century"}{"image_urls":[https://finds.org.uk/images/abolton/WAW-293C93.jpg],"from":-24,"to":260,"title":"WAW-293C93: A coin issued by Uncertain - 1st-mid 3rd century"}{"image_urls":[https://finds.org.uk/images/acooper/PAS_2444_Roman.jpg],"from":-24,"to":269,"title":"SWYOR-B44AFB: A coin issued by Uncertain - 1st-mid 3rd century"}{"image_urls":[https://finds.org.uk/images/abolton/WAW-E972E1.jpg],"from":-24,"to":260,"title":"WAW-E972E1: A coin issued by Uncertain - 1st-mid 3rd century"}{"image_urls":[https://finds.org.uk/images/abolton/WAW-295964.jpg],"from":-24,"to":260,"title":"WAW-295964: A coin issued by Uncertain - 1st-mid 3rd century"}{"image_urls":[https://finds.org.uk/images/preavill/HESH-B960AD.jpg],"from":-24,"to":260,"title":"HESH-B960A0: A coin issued by Uncertain - 1st-mid 3rd century"}{"image_urls":[https://finds.org.uk/images/abolton/WAW-68AC83.jpg],"from":-24,"to":269,"title":"WAW-68AC83: A coin issued by Uncertain - 1st-mid 3rd century"}{"image_urls":[https://finds.org.uk/images/abolton/WAW-D01B12.jpg],"from":-24,"to":260,"title":"WAW-D01B12: A coin issued by Uncertain - 1st-mid 3rd century"}{"image_urls":[https://finds.org.uk/images/abolton/WAW-6075E1.jpg],"from":-24,"to":250,"title":"WAW-6075E1: A coin issued by Uncertain - 1st-mid 3rd century"}{"image_urls":[https://finds.org.uk/images/dcrowther/PAS_1124_E914.jpg],"from":-24,"to":269,"title":"SWYOR-BCE914: A coin issued by Uncertain - 1st-mid 3rd century"}{"image_urls":[https://finds.org.uk/images/abolton/WAW-2389D7.jpg],"from":-24,"to":260,"title":"WAW-2389D7: A coin issued by Uncertain - 1st-mid 3rd century"}{"image_urls":[https://finds.org.uk/images/abolton/WAW-F68CD1.jpg],"from":-24,"to":200,"title":"WAW-F68CD1: A coin issued by Uncertain - 1st-mid 3rd century"}{"image_urls":[https://finds.org.uk/images/abolton/WAW-BE1FA6.jpg],"from":-24,"to":260,"title":"WAW-BE1FA6: A coin issued by Uncertain - 1st-mid 3rd century"}{"image_urls":[https://finds.org.uk/images/abolton/WAW-5BD691.jpg],"from":-24,"to":269,"title":"WAW-5BD691: A coin issued by Uncertain - 1st-mid 3rd century"}{"image_urls":[https://finds.org.uk/images/acooper/PAS_645_pos_autoninus_01.jpg],"from":-24,"to":269,"title":"SWYOR-5C1710: A coin issued by Antoninus Pius"}{"image_urls":[https://finds.org.uk/images/abolton/WAW-173598.jpg],"from":-24,"to":260,"title":"WAW-173598: A coin issued by Uncertain - 1st-mid 3rd century"}{"image_urls":[https://finds.org.uk/images/abolton/WAW-44C912.jpg],"from":-24,"to":250,"title":"WAW-44C912: A coin issued by Uncertain - 1st-mid 3rd century"}{"image_urls":[https://finds.org.uk/images/preavill/HESH-B94DE5.jpg],"from":-24,"to":260,"title":"HESH-B94DE5: A coin issued by Uncertain - 1st-mid 3rd century"}{"image_urls":[https://finds.org.uk/images/abolton/WAW6D45F8.jpg],"from":-24,"to":260,"title":"WAW-6D45F8: A coin issued by Uncertain - 1st-mid 3rd century"}{"image_urls":[https://finds.org.uk/images/abolton/WAW-5F3472.jpg],"from":-24,"to":269,"title":"WAW-5F3472: A coin issued by Uncertain - 1st-mid 3rd century"}{"image_urls":[https://finds.org.uk/images/tbrindle/WMID-731F04.jpg],"from":-26,"to":25,"title":"WMID-731F04: A coin issued by Cunobelin"}{"image_urls":[https://finds.org.uk/images/tbrindle/NARC-14D224quarterstater.jpg],"from":-26,"to":25,"title":"NARC-14D224: A coin issued by Tasciovanus"}{"image_urls":[https://finds.org.uk/images/abyard/2012107.jpg],"from":-26,"to":10,"title":"BERK-8FDD53: A coin issued by Tasciovanus"}{"image_urls":[https://finds.org.uk/images/maritime/226.%20Iron%20Age%20quarter%20stater%20Y226.jpg],"from":-26,"to":10,"title":"BERK-8E9197: A coin issued by Tasciovanus"}{"image_urls":[https://finds.org.uk/images/abyard/2013789.jpg],"from":-26,"to":10,"title":"BERK-10ECD5: A coin issued by Tasciovanus"}{"image_urls":[https://finds.org.uk/images/tbrindle/WMID-753AB4.jpg],"from":-26,"to":25,"title":"WMID-753AB4: A coin issued by Cunobelin"}{"image_urls":[https://finds.org.uk/images/strebor/PUBLIC-8ED912%20Iron%20Age%20Tasciovanus%20silver%20unit%20Boar.jpg],"from":-26,"to":10,"title":"PUBLIC-8ED912: A coin issued by Tasciovanus"}{"image_urls":[https://finds.org.uk/images/khindshamp/HAMP-DE0DEA.jpg],"from":-26,"to":10,"title":"HAMP-DE0DEA: A coin issued by Eppillus"}{"image_urls":[https://finds.org.uk/images/khindshamp/HAMP-A8011B.jpg],"from":-26,"to":10,"title":"HAMP-A8011B: A coin issued by Tincomarus"}{"image_urls":[https://finds.org.uk/images/jwatters/Iron%20Age%20coin%2004%20193%20-%204%20all.jpg],"from":-26,"to":10,"title":"BH-9D6A51: A coin issued by Tasciovanus"}{"image_urls":[https://finds.org.uk/images/rwebley2/PAS0B0BFB.jpg],"from":-26,"to":10,"title":"PAS-0B0BFB: A coin issued by Tasciovanus"}{"image_urls":[https://finds.org.uk/images/jcassidy/NARC-113E13b.jpg],"from":-26,"to":10,"title":"NARC-113E13: A coin with an unrecorded\/uncertain issuer."}{"image_urls":[https://finds.org.uk/images/jplouviez/WFL015sf843sf6865.jpg],"from":-26,"to":40,"title":"SF6865: A coin issued by Cunobelin"}{"image_urls":[https://finds.org.uk/images/yorkvol/BMR0249.jpg],"from":-27,"to":240,"title":"YORYM-1005A1: A coin issued by Caracalla"}{"image_urls":[http://numismatics.org/collectionimages/19501999/1953/1953.171.995.rev.width350.jpg],"from":-27,"to":14,"title":"Bronze As of Augustus, Rome, 27 BC - AD 14. 1953.171.995"}{"image_urls":[http://numismatics.org/collectionimages/19501999/1953/1953.171.1065.rev.width350.jpg],"from":-27,"to":14,"title":"Bronze Coin of Augustus, Lugdunum, 27 BC - AD 14. 1953.171.1065"}{"image_urls":[http://numismatics.org/collectionimages/19501999/1953/1953.171.980.rev.width350.jpg],"from":-27,"to":14,"title":"Bronze Dupondius of Augustus, Rome, 27 BC - AD 14. 1953.171.980"}{"image_urls":[http://numismatics.org/collectionimages/19001949/1944/1944.100.53364.rev.width350.jpg],"from":-27,"to":14,"title":"Bronze Dupondius of Augustus, Rome, 27 BC - AD 14. 1944.100.53364"}{"image_urls":[http://numismatics.org/collectionimages/19001949/1944/1944.100.53367.rev.width350.jpg],"from":-27,"to":14,"title":"Bronze As of Augustus, Rome, 27 BC - AD 14. 1944.100.53367"}{"image_urls":[http://numismatics.org/collectionimages/19501999/1953/1953.171.985.rev.width350.jpg],"from":-27,"to":14,"title":"Bronze As of Augustus, Rome, 27 BC - AD 14. 1953.171.985"}{"image_urls":[http://numismatics.org/collectionimages/19001949/1944/1944.100.53369.rev.width350.jpg],"from":-27,"to":14,"title":"Bronze As of Augustus, Rome, 27 BC - AD 14. 1944.100.53369"}{"image_urls":[http://numismatics.org/collectionimages/19001949/1944/1944.100.65544.rev.width350.jpg],"from":-27,"to":14,"title":"Bronze Coin, Antioch, 27 BC - AD 14. 1944.100.65544"}{"image_urls":[http://numismatics.org/collectionimages/19501999/1953/1953.171.988.rev.width350.jpg],"from":-27,"to":14,"title":"Bronze Sestertius of Augustus, Rome, 27 BC - AD 14. 1953.171.988"}{"image_urls":[http://numismatics.org/collectionimages/19001949/1944/1944.100.48376.rev.width350.jpg],"from":-27,"to":50,"title":"Silver drachm, Tabae, 27 BC - AD 50. 1944.100.48376"}{"image_urls":[http://numismatics.org/collectionimages/19501999/1953/1953.171.1014.rev.width350.jpg],"from":-27,"to":14,"title":"Bronze As of Augustus, Lugdunum, 27 BC - AD 14. 1953.171.1014"}{"image_urls":[http://numismatics.org/collectionimages/19501999/1953/1953.171.982.rev.width350.jpg],"from":-27,"to":14,"title":"Bronze As of Augustus, Rome, 27 BC - AD 14. 1953.171.982"}{"image_urls":[http://numismatics.org/collectionimages/19001949/1944/1944.100.53366.rev.width350.jpg],"from":-27,"to":14,"title":"Bronze As of Augustus, Rome, 27 BC - AD 14. 1944.100.53366"}{"image_urls":[http://numismatics.org/collectionimages/20002049/2008/2008.24.11.rev.width350.jpg],"from":-27,"to":37,"title":"Bronze dupondius, Thaena, 27 BC - AD 37. 2008.24.11"}{"image_urls":[http://numismatics.org/collectionimages/20002049/2008/2008.24.6.rev.width350.jpg],"from":-27,"to":14,"title":"Bronze Coin, Tralles, 27 BC - AD 14. 2008.24.6"}{"image_urls":[http://numismatics.org/collectionimages/19501999/1953/1953.171.1019.rev.width350.jpg],"from":-27,"to":14,"title":"Bronze As of Augustus, Lugdunum, 27 BC - AD 14. 1953.171.1019"}{"image_urls":[http://numismatics.org/collectionimages/19001949/1944/1944.100.53370.rev.width350.jpg],"from":-27,"to":14,"title":"Bronze As of Augustus, Rome, 27 BC - AD 14. 1944.100.53370"}{"image_urls":[http://numismatics.org/collectionimages/19501999/1953/1953.171.1017.rev.width350.jpg],"from":-27,"to":14,"title":"Bronze As of Augustus, Lugdunum, 27 BC - AD 14. 1953.171.1017"}{"image_urls":[http://numismatics.org/collectionimages/19001949/1944/1944.100.53372.rev.width350.jpg],"from":-27,"to":14,"title":"Bronze As of Augustus, Lugdunum, 27 BC - AD 14. 1944.100.53372"}{"image_urls":[http://numismatics.org/collectionimages/19501999/1953/1953.171.1011.rev.width350.jpg],"from":-27,"to":14,"title":"Bronze As of Augustus, Lugdunum, 27 BC - AD 14. 1953.171.1011"}{"image_urls":[http://numismatics.org/collectionimages/19501999/1953/1953.171.999.rev.width350.jpg],"from":-27,"to":14,"title":"Bronze As of Augustus, Rome, 27 BC - AD 14. 1953.171.999"}{"image_urls":[http://numismatics.org/collectionimages/19001949/1944/1944.100.65516.rev.width350.jpg],"from":-27,"to":14,"title":"Silver Tetradrachm of Augustus, Antioch, 27 BC - AD 14. 1944.100.65516"}{"image_urls":[http://numismatics.org/collectionimages/19501999/1953/1953.171.987.rev.width350.jpg],"from":-27,"to":14,"title":"Bronze As of Augustus, Rome, 27 BC - AD 14. 1953.171.987"}{"image_urls":[http://numismatics.org/collectionimages/19501999/1953/1953.171.1007.rev.width350.jpg],"from":-27,"to":14,"title":"Bronze As of Augustus, Lugdunum, 27 BC - AD 14. 1953.171.1007"}{"image_urls":[http://numismatics.org/collectionimages/19501999/1953/1953.171.1001.rev.width350.jpg],"from":-27,"to":14,"title":"Bronze As of Augustus, Rome, 27 BC - AD 14. 1953.171.1001"}{"image_urls":[http://numismatics.org/collectionimages/19501999/1953/1953.171.993.rev.width350.jpg],"from":-27,"to":14,"title":"Bronze As of Augustus, Rome, 27 BC - AD 14. 1953.171.993"}{"image_urls":[http://numismatics.org/collectionimages/19501999/1953/1953.171.1016.rev.width350.jpg],"from":-27,"to":14,"title":"Bronze As of Augustus, Lugdunum, 27 BC - AD 14. 1953.171.1016"}{"image_urls":[http://numismatics.org/collectionimages/19501999/1953/1953.171.715.rev.width350.jpg],"from":-27,"to":14,"title":"Bronze Coin, Antioch, 27 BC - AD 14. 1953.171.715"}{"image_urls":[http://numismatics.org/collectionimages/19501999/1953/1953.171.1004.rev.width350.jpg],"from":-27,"to":14,"title":"Bronze As of Augustus, Lugdunum, 27 BC - AD 14. 1953.171.1004"}{"image_urls":[http://numismatics.org/collectionimages/19501999/1953/1953.171.1010.rev.width350.jpg],"from":-27,"to":14,"title":"Bronze As of Augustus, Lugdunum, 27 BC - AD 14. 1953.171.1010"}{"image_urls":[http://numismatics.org/collectionimages/19001949/1944/1944.100.53365.rev.width350.jpg],"from":-27,"to":14,"title":"Bronze As of Augustus, Rome, 27 BC - AD 14. 1944.100.53365"}{"image_urls":[http://numismatics.org/collectionimages/19501999/1953/1953.171.1005.rev.width350.jpg],"from":-27,"to":14,"title":"Bronze As of Augustus, Lugdunum, 27 BC - AD 14. 1953.171.1005"}{"image_urls":[http://numismatics.org/collectionimages/19501999/1953/1953.171.997.rev.width350.jpg],"from":-27,"to":14,"title":"Bronze As of Augustus, Rome, 27 BC - AD 14. 1953.171.997"}{"image_urls":[http://numismatics.org/collectionimages/19501999/1953/1953.171.1008.rev.width350.jpg],"from":-27,"to":14,"title":"Bronze As of Augustus, Lugdunum, 27 BC - AD 14. 1953.171.1008"}{"image_urls":[http://numismatics.org/collectionimages/19501999/1953/1953.171.981.rev.width350.jpg],"from":-27,"to":14,"title":"Bronze As of Augustus, Rome, 27 BC - AD 14. 1953.171.981"}{"image_urls":[http://numismatics.org/collectionimages/19501999/1953/1953.171.996.rev.width350.jpg],"from":-27,"to":14,"title":"Bronze As of Augustus, Rome, 27 BC - AD 14. 1953.171.996"}{"image_urls":[http://numismatics.org/collectionimages/19001949/1944/1944.100.53371.rev.width350.jpg],"from":-27,"to":14,"title":"Bronze As of Augustus, Rome, 27 BC - AD 14. 1944.100.53371"}{"image_urls":[http://numismatics.org/collectionimages/19501999/1953/1953.171.1066.rev.width350.jpg],"from":-27,"to":14,"title":"Bronze Coin of Augustus, Lugdunum, 27 BC - AD 14. 1953.171.1066"}{"image_urls":[http://numismatics.org/collectionimages/19501999/1953/1953.171.990.rev.width350.jpg],"from":-27,"to":14,"title":"Bronze As of Augustus, Rome, 27 BC - AD 14. 1953.171.990"}{"image_urls":[http://numismatics.org/collectionimages/19501999/1953/1953.171.984.rev.width350.jpg],"from":-27,"to":14,"title":"Bronze Sestertius of Augustus, Rome, 27 BC - AD 14. 1953.171.984"}{"image_urls":[http://numismatics.org/collectionimages/19001949/1944/1944.100.53368.rev.width350.jpg],"from":-27,"to":14,"title":"Bronze As of Augustus, Rome, 27 BC - AD 14. 1944.100.53368"}{"image_urls":[http://numismatics.org/collectionimages/19501999/1953/1953.171.1006.rev.width350.jpg],"from":-27,"to":14,"title":"Bronze As of Augustus, Lugdunum, 27 BC - AD 14. 1953.171.1006"}{"image_urls":[http://numismatics.org/collectionimages/00001899/0000/0000.999.23706.rev.width350.jpg],"from":-27,"to":14,"title":"Bronze As of Augustus, Rome, 27 BC - AD 14. 0000.999.23706"}{"image_urls":[http://numismatics.org/collectionimages/19501999/1953/1953.171.717.rev.width350.jpg],"from":-27,"to":14,"title":"Bronze Coin, Antioch, 27 BC - AD 14. 1953.171.717"}{"image_urls":[http://numismatics.org/collectionimages/19501999/1953/1953.171.1012.rev.width350.jpg],"from":-27,"to":14,"title":"Bronze As of Augustus, Lugdunum, 27 BC - AD 14. 1953.171.1012"}{"image_urls":[http://numismatics.org/collectionimages/19501999/1953/1953.171.1018.rev.width350.jpg],"from":-27,"to":14,"title":"Bronze As of Augustus, Lugdunum, 27 BC - AD 14. 1953.171.1018"}{"image_urls":[http://numismatics.org/collectionimages/19501999/1953/1953.171.1003.rev.width350.jpg],"from":-27,"to":14,"title":"Bronze As of Augustus, Lugdunum, 27 BC - AD 14. 1953.171.1003"}{"image_urls":[http://numismatics.org/collectionimages/19501999/1953/1953.171.1000.rev.width350.jpg],"from":-27,"to":14,"title":"Bronze As of Augustus, Rome, 27 BC - AD 14. 1953.171.1000"}{"image_urls":[http://numismatics.org/collectionimages/19501999/1953/1953.171.1009.rev.width350.jpg],"from":-27,"to":14,"title":"Bronze As of Augustus, Lugdunum, 27 BC - AD 14. 1953.171.1009"}{"image_urls":[http://numismatics.org/collectionimages/19501999/1953/1953.171.986.rev.width350.jpg],"from":-27,"to":14,"title":"Bronze As of Augustus, Rome, 27 BC - AD 14. 1953.171.986"}{"image_urls":[http://numismatics.org/collectionimages/19501999/1953/1953.171.992.rev.width350.jpg],"from":-27,"to":14,"title":"Bronze As of Augustus, Rome, 27 BC - AD 14. 1953.171.992"}{"image_urls":[http://numismatics.org/collectionimages/19001949/1944/1944.100.53373.rev.width350.jpg],"from":-27,"to":14,"title":"Bronze As of Augustus, Lugdunum, 27 BC - AD 14. 1944.100.53373"}{"image_urls":[http://numismatics.org/collectionimages/19501999/1953/1953.171.994.rev.width350.jpg],"from":-27,"to":14,"title":"Bronze As of Augustus, Rome, 27 BC - AD 14. 1953.171.994"}{"image_urls":[http://numismatics.org/collectionimages/19501999/1953/1953.171.1002.rev.width350.jpg],"from":-27,"to":14,"title":"Bronze As of Augustus, Rome, 27 BC - AD 14. 1953.171.1002"}{"image_urls":[https://finds.org.uk/images/bmorris/CR0104.jpg],"from":-28,"to":260,"title":"YORYM-439360: A coin issued by Uncertain - 1st-mid 3rd century"}{"image_urls":[https://finds.org.uk/images/bmorris/CR0073.jpg],"from":-28,"to":260,"title":"YORYM-7715A1: A coin issued by Uncertain - 1st-mid 3rd century"}{"image_urls":[https://finds.org.uk/images/bmorris/KSB0293.jpg],"from":-28,"to":240,"title":"YORYM-E955C6: A coin issued by Uncertain - 1st-mid 3rd century"}{"image_urls":[https://finds.org.uk/images/bmorris/WSB0006.jpg],"from":-28,"to":260,"title":"YORYM-1D8357: A coin issued by Uncertain - 1st-mid 3rd century"}{"image_urls":[https://finds.org.uk/images/bmorris/MW0102.jpg],"from":-28,"to":269,"title":"YORYM-10A768: A coin issued by Uncertain - 1st-mid 3rd century"}{"image_urls":[https://finds.org.uk/images/bmorris/SW0005.jpg],"from":-28,"to":269,"title":"YORYM-1CB7F1: A coin issued by Uncertain - 1st-mid 3rd century"}{"image_urls":[https://finds.org.uk/images/bmorris/CR0103.jpg],"from":-28,"to":260,"title":"YORYM-437D90: A coin issued by Uncertain - 1st-mid 3rd century"}{"image_urls":[https://finds.org.uk/images/tclifford/A-238.jpg],"from":-28,"to":96,"title":"SUSS-5FD9D5: A coin issued by Augustus"}{"image_urls":[https://finds.org.uk/images/abolton/WAW-E936B6.jpg],"from":-28,"to":240,"title":"WAW-E936B6: A coin issued by Uncertain - 1st-mid 3rd century"}{"image_urls":[https://finds.org.uk/images/bmorris/AC0016a.jpg],"from":-28,"to":260,"title":"YORYM-B883A6: A coin issued by Uncertain - 1st-mid 3rd century"}{"image_urls":[https://finds.org.uk/images/gburr/DSCN5895.JPG],"from":-28,"to":54,"title":"KENT-D065C0: A coin issued by Augustus"}{"image_urls":[https://finds.org.uk/images/bmorris/AC0032.jpg],"from":-28,"to":260,"title":"YORYM-CBD7F5: A coin issued by Uncertain - 1st-mid 3rd century"}{"image_urls":[https://finds.org.uk/images/dwilliams/07.03.JPG],"from":-28,"to":14,"title":"SUR-9B28B1: A coin issued by Augustus"}{"image_urls":[https://finds.org.uk/images/bmorris/TMY0018.jpg],"from":-28,"to":269,"title":"YORYM-7D1731: A coin issued by Uncertain - 1st-mid 3rd century"}{"image_urls":[https://finds.org.uk/images/nherepath/589837.jpg],"from":-28,"to":240,"title":"LVPL-5E9837: A coin issued by Trajan"}{"image_urls":[https://finds.org.uk/images/bmorris/DB0175.jpg],"from":-28,"to":260,"title":"YORYM-CBF576: A coin issued by Uncertain - 1st-mid 3rd century"}{"image_urls":[https://finds.org.uk/images/margaretb/13-1160.JPG],"from":-28,"to":14,"title":"SUR-B33787: A coin issued by Augustus"}{"image_urls":[https://finds.org.uk/images/bmorris/AC0033.jpg],"from":-28,"to":260,"title":"YORYM-CBEE38: A coin issued by Uncertain - 1st-mid 3rd century"}{"image_urls":[https://finds.org.uk/images/bmorris/RJ0014.jpg],"from":-28,"to":260,"title":"YORYM-2FFA98: A coin issued by Uncertain - 1st-mid 3rd century"}{"image_urls":[https://finds.org.uk/images/abolton/WAW-11DD83.jpg],"from":-28,"to":269,"title":"WAW-11DD83: A coin issued by Uncertain - 1st-mid 3rd century"}{"image_urls":[https://finds.org.uk/images/bmorris/DE0113.jpg],"from":-28,"to":260,"title":"YORYM-22EAD7: A coin issued by Uncertain - 1st-mid 3rd century"}{"image_urls":[https://finds.org.uk/images/dwootton/TEd%20godfery%20denarius%20fragment.jpg],"from":-3,"to":14,"title":"DEV-8589B2: A coin issued by Augustus"}{"image_urls":[https://finds.org.uk/images/jplouviez/COM026SF-A05047.JPG],"from":-3,"to":14,"title":"SF-A05047: A coin issued by Augustus"}{"image_urls":[https://finds.org.uk/images/abyard/2013378.jpg],"from":-3,"to":14,"title":"BERK-A3A9D1: A coin issued by Augustus"}{"image_urls":[https://finds.org.uk/images/gstewart/WRW_SF-E3C891.jpg],"from":-3,"to":14,"title":"SF-E3C891: A coin issued by Augustus"}{"image_urls":[https://finds.org.uk/images/sworrell/hamp%203396.JPG],"from":-3,"to":14,"title":"HAMP3396: A coin issued by Augustus"}{"image_urls":[https://finds.org.uk/images/wakefield/PAS_1148_IAcoin.jpg],"from":-31,"to":30,"title":"SWYOR-56CA22: A coin issued by Tasciovanus"}{"image_urls":[https://finds.org.uk/images/eloisemarkwick/WAW-D5B5A1.jpg],"from":-31,"to":50,"title":"WAW-D5B5A1: A coin issued by Uncertain - 1st\/2nd Century AD"}{"image_urls":[http://numismatics.org/collectionimages/19001949/1944/1944.100.62255.rev.width350.jpg],"from":-31,"to":14,"title":"Bronze Coin, Pessinus, 31 BC - AD 14. 1944.100.62255"}{"image_urls":[http://numismatics.org/collectionimages/19001949/1944/1944.100.62254.rev.width350.jpg],"from":-31,"to":14,"title":"Bronze Coin, Pessinus, 31 BC - AD 14. 1944.100.62254"}{"image_urls":[http://numismatics.org/collectionimages/19001949/1944/1944.100.10307.rev.width350.jpg],"from":-31,"to":14,"title":"Bronze Coin, Amphipolis, 31 BC - AD 14. 1944.100.10307"}{"image_urls":[http://numismatics.org/collectionimages/19001949/1944/1944.100.70218.rev.width350.jpg],"from":-31,"to":14,"title":"Bronze Coin, Berytus, 31 BC - AD 14. 1944.100.70218"}{"image_urls":[http://numismatics.org/collectionimages/20002049/2013/2013.65.5.rev.width350.jpg],"from":-36,"to":37,"title":"Bronze As of C.I.L.C.Q, Emporiae, 36 BC - AD 37. 2013.65.5"}{"image_urls":[http://numismatics.org/collectionimages/20002049/2013/2013.65.6.rev.width350.jpg],"from":-36,"to":37,"title":"Bronze Quadrans of Anonymous, Emporiae, 36 BC - AD 37. 2013.65.6"}{"image_urls":[http://numismatics.org/collectionimages/19001949/1944/1944.100.62833.rev.width350.jpg],"from":-4,"to":34,"title":"Bronze Coin, Caesareia Panias, 4 BC - AD 34. 1944.100.62833"}{"image_urls":[http://numismatics.org/collectionimages/19001949/1944/1944.100.62828.rev.width350.jpg],"from":-4,"to":39,"title":"Bronze Coin, Tiberias, 4 BC - AD 39. 1944.100.62828"}{"image_urls":[http://numismatics.org/collectionimages/19001949/1944/1944.100.62825.rev.width350.jpg],"from":-4,"to":39,"title":"Bronze Coin, Tiberias, 4 BC - AD 39. 1944.100.62825"}{"image_urls":[http://numismatics.org/collectionimages/00001899/0000/0000.999.25755.rev.width350.jpg],"from":-4,"to":34,"title":"Bronze Coin, Caesareia Panias, 4 BC - AD 34. 0000.999.25755"}{"image_urls":[http://numismatics.org/collectionimages/19001949/1944/1944.100.62827.rev.width350.jpg],"from":-4,"to":39,"title":"Bronze Coin, Tiberias, 4 BC - AD 39. 1944.100.62827"}{"image_urls":[http://numismatics.org/collectionimages/19001949/1944/1944.100.62836.rev.width350.jpg],"from":-4,"to":34,"title":"Bronze Coin, Caesareia Panias, 4 BC - AD 34. 1944.100.62836"}{"image_urls":[http://numismatics.org/collectionimages/19001949/1944/1944.100.62834.rev.width350.jpg],"from":-4,"to":34,"title":"Bronze Coin, Caesareia Panias, 4 BC - AD 34. 1944.100.62834"}{"image_urls":[http://numismatics.org/collectionimages/19001949/1944/1944.100.62832.rev.width350.jpg],"from":-4,"to":34,"title":"Bronze Coin, Caesareia Panias, 4 BC - AD 34. 1944.100.62832"}{"image_urls":[http://numismatics.org/collectionimages/19001949/1944/1944.100.62826.rev.width350.jpg],"from":-4,"to":39,"title":"Bronze Coin, Tiberias, 4 BC - AD 39. 1944.100.62826"}{"image_urls":[http://numismatics.org/collectionimages/19001949/1944/1944.100.62835.rev.width350.jpg],"from":-4,"to":34,"title":"Bronze Coin, Caesareia Panias, 4 BC - AD 34. 1944.100.62835"}{"image_urls":[https://finds.org.uk/images/lbuckley/Dscn9115.jpg],"from":-44,"to":410,"title":"BUC-A0E207: A coin issued by Gallienus (sole reign)"}{"image_urls":[https://finds.org.uk/images/lbuckley/DSCN8668.JPG],"from":-44,"to":410,"title":"BUC-543FF5: A coin issued by Allectus"}{"image_urls":[http://numismatics.org/collectionimages/19001949/1944/1944.100.17715.rev.width350.jpg],"from":-44,"to":14,"title":"Bronze Coin, Larissa, 44 BC - AD 14. 1944.100.17715"}{"image_urls":[http://numismatics.org/collectionimages/19001949/1944/1944.100.17726.rev.width350.jpg],"from":-44,"to":14,"title":"Bronze Coin, Larissa, 44 BC - AD 14. 1944.100.17726"}{"image_urls":[http://numismatics.org/collectionimages/19501999/1953/1953.171.1481.rev.width350.jpg],"from":-44,"to":14,"title":"Bronze Coin, Antioch, 44 BC - AD 14. 1953.171.1481"}{"image_urls":[http://numismatics.org/collectionimages/19001949/1944/1944.100.17727.rev.width350.jpg],"from":-44,"to":14,"title":"Bronze Coin, Larissa, 44 BC - AD 14. 1944.100.17727"}{"image_urls":[http://numismatics.org/collectionimages/19001949/1944/1944.100.17717.rev.width350.jpg],"from":-44,"to":14,"title":"Bronze Coin, Larissa, 44 BC - AD 14. 1944.100.17717"}{"image_urls":[http://numismatics.org/collectionimages/19001949/1944/1944.100.65545.rev.width350.jpg],"from":-44,"to":14,"title":"Bronze Coin, Antioch, 44 BC - AD 14. 1944.100.65545"}{"image_urls":[http://numismatics.org/collectionimages/19501999/1963/1963.2.1.rev.width350.jpg],"from":-44,"to":14,"title":"Bronze Coin, Larissa, 44 BC - AD 14. 1963.2.1"}{"image_urls":[http://numismatics.org/collectionimages/19501999/1953/1953.171.1480.rev.width350.jpg],"from":-44,"to":14,"title":"Bronze Coin, Antioch, 44 BC - AD 14. 1953.171.1480"}{"image_urls":[http://numismatics.org/collectionimages/19001949/1944/1944.100.65546.rev.width350.jpg],"from":-44,"to":14,"title":"Bronze Coin, Antioch, 44 BC - AD 14. 1944.100.65546"}{"image_urls":[http://numismatics.org/collectionimages/19001949/1944/1944.100.66588.rev.width350.jpg],"from":-44,"to":14,"title":"Silver Tetradrachm, Seleuceia Pieria, 44 BC - AD 14. 1944.100.66588"}{"image_urls":[https://finds.org.uk/images/rharte/NARC-4090C2%28s%29.jpg],"from":-51,"to":50,"title":"NARC-4090C2: A coin issued by Cunobelin"}{"image_urls":[https://finds.org.uk/images/rharte/narc805.jpg],"from":-51,"to":43,"title":"NARC805: A coin issued by Tasciovanus"}{"image_urls":[https://finds.org.uk/images/ksumnall/Kennedy-Griffincoin-Sept12.jpg],"from":-51,"to":50,"title":"LON-19AD01: A coin issued by Cunobelin"}{"image_urls":[https://finds.org.uk/images/rharte/narc1163.jpg],"from":-51,"to":43,"title":"NARC1163: A coin issued by Cunobelin"}{"image_urls":[https://finds.org.uk/images/dwilliams/B15275a.JPG],"from":-51,"to":43,"title":"SUR-8F755A: A coin issued by Tincomarus"}{"image_urls":[https://finds.org.uk/images/tgilmore/LVPL-4C2107.jpg],"from":-51,"to":43,"title":"LVPL-4C2107: A coin issued by Eppillus"}{"image_urls":[https://finds.org.uk/images/ksumnall/Kennedy-Januscoin-Sept12.jpg],"from":-51,"to":50,"title":"LON-1968A6: A coin issued by Cunobelin"}{"image_urls":[https://finds.org.uk/images/jwatters/IA%201%20obv.jpg],"from":-51,"to":44,"title":"BH-D71D91: A coin issued by Cunobelin"}{"image_urls":[https://finds.org.uk/images/ksumnall/Robson%20-%20quarter%20stater%20-%20June%2007.jpg],"from":-51,"to":50,"title":"LON-5566B3: A coin issued by Cunobelin"}{"image_urls":[https://finds.org.uk/images/dwilliams/07.148.JPG],"from":-7,"to":14,"title":"SUR-289696: A coin issued by Augustus"}{"image_urls":[https://finds.org.uk/images/cjohnson/WMID-03E646%20obv.jpg],"from":-8,"to":14,"title":"WMID-03E646: A coin issued by Augustus"}{"image_urls":[http://coins.lib.virginia.edu/images/coins/screen/nfic_50_55_rev.jpg],"from":-9,"to":40,"title":"Coin of Aretas IV, Petra, 9 B.C.-A.D. 40. FIC.50.55."}{"image_urls":[http://coins.lib.virginia.edu/images/coins/screen/nfic_50_54_rev.jpg],"from":-9,"to":40,"title":"Coin of Aretas IV, Petra, 9 B.C.-A.D. 40. FIC.50.54."}{"image_urls":[https://finds.org.uk/images/khindshamp/HAMPB68B2C.jpg],"from":1,"to":200,"title":"HAMP-B68B2C: A coin issued by Uncertain - 1st\/2nd Century AD"}{"image_urls":[https://finds.org.uk/images/jwatters/Roman_coin_14_108_12.jpg],"from":1,"to":275,"title":"BH-5A5B6B: A coin issued by Uncertain - 1st-mid 3rd century"}{"image_urls":[https://finds.org.uk/images/lwalker/SUSS-17BB0D.jpg],"from":1,"to":250,"title":"SUSS-17BB0D: A coin issued by Uncertain - 1st-mid 3rd century"}{"image_urls":[https://finds.org.uk/images/lwalker/SUSS-5EBF64.jpg],"from":1,"to":250,"title":"SUSS-5EBF64: A coin issued by Uncertain - 1st-mid 3rd century"}{"image_urls":[https://finds.org.uk/images/tgilmore/WMID-B0A519.jpg],"from":1,"to":300,"title":"WMID-B0A519: A coin issued by Uncertain - 1st-mid 3rd century"}{"image_urls":[https://finds.org.uk/images/lwalker/SUSS-5EFF9D.jpg],"from":1,"to":250,"title":"SUSS-5EFF9D: A coin issued by Uncertain - 1st-mid 3rd century"}{"image_urls":[https://finds.org.uk/images/tgilmore/WMID9E9FA4.jpg],"from":1,"to":300,"title":"WMID-9E9FA4: A coin issued by Uncertain - 1st-mid 3rd century"}{"image_urls":[https://finds.org.uk/images/stephaniesmith/SUSSFCF25E.jpg],"from":1,"to":250,"title":"SUSS-FCF25E: A coin issued by Uncertain - 1st-mid 3rd century"}{"image_urls":[https://finds.org.uk/images/stephaniesmith/SUSS-FD233E.jpg],"from":1,"to":250,"title":"SUSS-FD233E: A coin issued by Uncertain - 1st-mid 3rd century"}{"image_urls":[https://finds.org.uk/images/tgilmore/WMID-301230.jpg],"from":1,"to":200,"title":"WMID-301230: A coin issued by Uncertain - 1st-mid 3rd century"}{"image_urls":[https://finds.org.uk/images/jplouviez/WFL015SF-EB6D67.jpg],"from":1,"to":40,"title":"SF-EB6D67: A coin issued by Cunobelin"}{"image_urls":[https://finds.org.uk/images/stephaniesmith/SUSS-D10400.jpg],"from":1,"to":250,"title":"SUSS-D10400: A coin issued by Uncertain - 1st-mid 3rd century"}{"image_urls":[https://finds.org.uk/images/abrown/EXG_SF-4876EE.jpg],"from":1,"to":42,"title":"SF-4876EE: A coin issued by Cunobelin"}{"image_urls":[https://finds.org.uk/images/abrown/LVM_SF-813F85.jpg],"from":1,"to":43,"title":"SF-813F85: A coin issued by Cunobelin"}{"image_urls":[https://finds.org.uk/images/stephaniesmith/SUSS-97952D.jpg],"from":1,"to":250,"title":"SUSS-97952D: A coin issued by Uncertain - 1st-mid 3rd century"}{"image_urls":[https://finds.org.uk/images/stephaniesmith/SUSS-78B8EF.jpg],"from":1,"to":250,"title":"SUSS-78B8EF: A coin issued by Uncertain - 1st-mid 3rd century"}{"image_urls":[https://finds.org.uk/images/tgilmore/WMID7CCC9C.jpg],"from":1,"to":250,"title":"WMID-7CCC9C: A coin issued by Uncertain - 1st-mid 3rd century"}{"image_urls":[https://finds.org.uk/images/lwalker/SUSS-688556.jpg],"from":1,"to":250,"title":"SUSS-688556: A coin issued by Uncertain - 1st-mid 3rd century"}{"image_urls":[https://finds.org.uk/images/lburnett/SUSS-DB4CF6.jpg],"from":1,"to":250,"title":"SUSS-DB4CF6: A coin issued by Uncertain - 1st-mid 3rd century"}{"image_urls":[https://finds.org.uk/images/jcarr/BKY%20SF-4576A6.jpg],"from":1,"to":40,"title":"SF-4576A6: A coin issued by Cunobelin"}{"image_urls":[https://finds.org.uk/images/tgilmore/WMID7CA113.jpg],"from":1,"to":250,"title":"WMID-7CA113: A coin issued by Uncertain - 1st-mid 3rd century"}{"image_urls":[https://finds.org.uk/images/stephaniesmith/SUSSF50B40.jpg],"from":1,"to":250,"title":"SUSS-F50B40: A coin issued by Uncertain - 1st-mid 3rd century"}{"image_urls":[https://finds.org.uk/images/stephaniesmith/SUSS-5A4B13.jpg],"from":1,"to":250,"title":"SUSS-5A4B13: A coin issued by Uncertain - 1st-mid 3rd century"}{"image_urls":[https://finds.org.uk/images/voakden/LVPL-DA94E0.JPG],"from":1,"to":250,"title":"LVPL-DA94E0: A coin issued by Uncertain - 1st-mid 3rd century"}{"image_urls":[https://finds.org.uk/images/32midhurst/Sesterius%20%28640x343%29.jpg],"from":1,"to":250,"title":"PUBLIC-58CCC4: A coin issued by Uncertain - 1st-mid 3rd century"}{"image_urls":[https://finds.org.uk/images/voakden/LVPL-A91246.JPG],"from":1,"to":250,"title":"LVPL-A91246: A coin issued by Uncertain - 1st-mid 3rd century"}{"image_urls":[https://finds.org.uk/images/tgilmore/WMID-D60F94.jpg],"from":1,"to":200,"title":"WMID-D60F94: A coin issued by Uncertain - 1st-mid 3rd century"}{"image_urls":[https://finds.org.uk/images/tgilmore/WMID-1D7F81.jpg],"from":1,"to":300,"title":"WMID-1D7F81: A coin issued by Uncertain - 1st-mid 3rd century"}{"image_urls":[https://finds.org.uk/images/voakden/LVPL-F91165.jpg],"from":1,"to":250,"title":"LVPL-F91165: A coin issued by Uncertain - 1st-mid 3rd century"}{"image_urls":[https://finds.org.uk/images/dwilliams/07.620.JPG],"from":1,"to":40,"title":"SUR-E989C1: A coin issued by Cunobelin"}{"image_urls":[https://finds.org.uk/images/stephaniesmith/SUSS-CC10E1.jpg],"from":1,"to":250,"title":"SUSS-CC10E1: A coin issued by Uncertain - 1st-mid 3rd century"}{"image_urls":[https://finds.org.uk/images/karend1/KENT-15E6E5.jpg],"from":1,"to":250,"title":"KENT-15E6E5: A coin issued by Uncertain - 1st-mid 3rd century"}{"image_urls":[https://finds.org.uk/images/stephaniesmith/SUSS-041A91DorAUncertain.jpg],"from":1,"to":250,"title":"SUSS-041A91: A coin issued by Uncertain - 1st-mid 3rd century"}{"image_urls":[https://finds.org.uk/images/nherepath/lvpl23.jpg],"from":1,"to":40,"title":"LVPL23: A coin issued by Cunobelin"}{"image_urls":[https://finds.org.uk/images/voakden/LVPL-714851.JPG],"from":1,"to":250,"title":"LVPL-714851: A coin issued by Uncertain - 1st-mid 3rd century"}{"image_urls":[https://finds.org.uk/images/abolton/WAW-9DA72A.jpg],"from":1,"to":250,"title":"WAW-9DA72A: A coin issued by Uncertain - 1st-mid 3rd century"}{"image_urls":[https://finds.org.uk/images/lwalker/SUSS-864621.jpg],"from":1,"to":250,"title":"SUSS-864621: A coin issued by Uncertain - 1st-mid 3rd century"}{"image_urls":[https://finds.org.uk/images/stephaniesmith/SUSS-5A2774.jpg],"from":1,"to":250,"title":"SUSS-5A2774: A coin issued by Uncertain - 1st-mid 3rd century"}{"image_urls":[https://finds.org.uk/images/karend1/KENT-821B18.jpg],"from":1,"to":250,"title":"KENT-821B18: A coin issued by Uncertain - 1st-mid 3rd century"}{"image_urls":[https://finds.org.uk/images/jplouviez/WKS003SF-5F6E40.JPG],"from":1,"to":42,"title":"SF-5F6E40: A coin issued by Cunobelin"}{"image_urls":[https://finds.org.uk/images/stephaniesmith/SUSSF207B5.jpg],"from":1,"to":200,"title":"SUSS-F207B5: A coin issued by Uncertain - 1st\/2nd Century AD"}{"image_urls":[https://finds.org.uk/images/dwilliams/B15274.JPG],"from":1,"to":43,"title":"SUR-8F655D: A coin issued by Verica"}{"image_urls":[https://finds.org.uk/images/cburrill2/E7881_Dupondius.jpg],"from":1,"to":250,"title":"DENO-8510F7: A coin issued by Uncertain - 1st-mid 3rd century"}{"image_urls":[https://finds.org.uk/images/mforeman/NLM27466.jpg],"from":1,"to":260,"title":"NLM-67F3A1: A coin issued by Uncertain - 1st-mid 3rd century"}{"image_urls":[https://finds.org.uk/images/voakden/LVPL-130974.JPG],"from":1,"to":250,"title":"LVPL-130974: A coin issued by Uncertain - 1st-mid 3rd century"}{"image_urls":[https://finds.org.uk/images/voakden/LVPL-F8F3F1.jpg],"from":1,"to":250,"title":"LVPL-F8F3F1: A coin issued by Uncertain - 1st-mid 3rd century"}{"image_urls":[https://finds.org.uk/images/tgilmore/wmid-d5f863.jpg],"from":1,"to":200,"title":"WMID-D5F863: A coin issued by Uncertain - 1st-mid 3rd century"}{"image_urls":[https://finds.org.uk/images/stephaniesmith/SUSS-998421.jpg],"from":1,"to":250,"title":"SUSS-998421: A coin issued by Uncertain - 1st-mid 3rd century"}{"image_urls":[https://finds.org.uk/images/tgilmore/WMID7CEF44.jpg],"from":1,"to":250,"title":"WMID-7CEF44: A coin issued by Uncertain - 1st-mid 3rd century"}{"image_urls":[https://finds.org.uk/images/lwalker/SUSS-17AAA4.jpg],"from":1,"to":250,"title":"SUSS-17AAA4: A coin issued by Uncertain - 1st-mid 3rd century"}{"image_urls":[https://finds.org.uk/images/jplouviez/COL%20SF-494084.jpg],"from":1,"to":40,"title":"SF-494084: A coin issued by Cunobelin"}{"image_urls":[https://finds.org.uk/images/abyard/2011409.jpg],"from":1,"to":10,"title":"BERK-A22111: A coin issued by RVES"}{"image_urls":[https://finds.org.uk/images/tgilmore/WMID-1C0583.jpg],"from":1,"to":200,"title":"WMID-1C0583: A coin issued by Uncertain - 1st-mid 3rd century"}{"image_urls":[https://finds.org.uk/images/stephaniesmith/SUSS-865F5A.jpg],"from":1,"to":250,"title":"SUSS-865F5A: A coin issued by Uncertain - 1st-mid 3rd century"}{"image_urls":[https://finds.org.uk/images/rwebley/HAMP-9FA9F4Julio-Claudianas.jpg],"from":1,"to":50,"title":"HAMP-9FA9F4: A coin issued by Julio-Claudian (uncertain)"}{"image_urls":[https://finds.org.uk/images/stephaniesmith/SUSS-A53DF7.jpg],"from":1,"to":250,"title":"SUSS-A53DF7: A coin issued by Uncertain - 1st-mid 3rd century"}{"image_urls":[https://finds.org.uk/images/voakden/LVPL-F8B882.jpg],"from":1,"to":250,"title":"LVPL-F8B882: A coin issued by Uncertain - 1st-mid 3rd century"}{"image_urls":[https://finds.org.uk/images/helenglenn3/DENO3C39E1.jpg],"from":1,"to":250,"title":"DENO-3C39E1: A coin issued by Uncertain - 1st-mid 3rd century"}{"image_urls":[https://finds.org.uk/images/jwatters/Roman_coin_13_56_8.jpg],"from":1,"to":200,"title":"BH-625167: A coin issued by Uncertain - 1st\/2nd Century AD"}{"image_urls":[https://finds.org.uk/images/voakden/LVPL-F84F42.jpg],"from":1,"to":250,"title":"LVPL-F84F42: A coin issued by Uncertain - 1st-mid 3rd century"}{"image_urls":[https://finds.org.uk/images/tgilmore/WMID48567F.jpg],"from":1,"to":250,"title":"WMID-48567F: A coin issued by Uncertain - 1st-mid 3rd century"}{"image_urls":[https://finds.org.uk/images/voakden/LVPL-C62292.jpg],"from":1,"to":250,"title":"LVPL-C62292: A coin issued by Uncertain - 1st-mid 3rd century"}{"image_urls":[https://finds.org.uk/images/stephaniesmith/SUSS-CC0011.jpg],"from":1,"to":250,"title":"SUSS-CC0011: A coin issued by Uncertain - 1st-mid 3rd century"}{"image_urls":[https://finds.org.uk/images/tgilmore/WMID-1C930E.jpg],"from":1,"to":300,"title":"WMID-1C930E: A coin issued by Uncertain - 1st-mid 3rd century"}{"image_urls":[https://finds.org.uk/images/helenglenn3/DENOA31E34.jpg],"from":1,"to":300,"title":"DENO-A31E34: A coin issued by Uncertain - 1st-mid 3rd century"}{"image_urls":[https://finds.org.uk/images/tgilmore/WMID-890E42.jpg],"from":1,"to":200,"title":"WMID-890E42: A coin issued by Uncertain - 1st-mid 3rd century"}{"image_urls":[https://finds.org.uk/images/stephaniesmith/SUSS-977282.jpg],"from":1,"to":250,"title":"SUSS-977282: A coin issued by Uncertain - 1st-mid 3rd century"}{"image_urls":[https://finds.org.uk/images/stephaniesmith/SUSSA25147.jpg],"from":1,"to":250,"title":"SUSS-A25147: A coin issued by Uncertain - 1st-mid 3rd century"}{"image_urls":[https://finds.org.uk/images/tgilmore/WMID-6B220F.jpg],"from":1,"to":250,"title":"WMID-6B220F: A coin with an unrecorded\/uncertain issuer."}{"image_urls":[https://finds.org.uk/images/tgilmore/WMID-1156A1.jpg],"from":1,"to":250,"title":"WMID-1156A1: A coin issued by Faustina II under Antoninus Pius"}{"image_urls":[https://finds.org.uk/images/jplouviez/COL%20SF-4BF1A3.jpg],"from":1,"to":25,"title":"SF-4BF1A3: A coin issued by Cunobelin"}{"image_urls":[https://finds.org.uk/images/carolinechestnutt/SUSS-FCE393.jpg],"from":1,"to":250,"title":"SUSS-FCE393: A coin issued by Uncertain - 1st-mid 3rd century"}{"image_urls":[https://finds.org.uk/images/jplouviez/COMSF-584425.JPG],"from":1,"to":40,"title":"SF-584425: A coin issued by Cunobelin"}{"image_urls":[https://finds.org.uk/images/tgilmore/WMID7CBE01.jpg],"from":1,"to":250,"title":"WMID-7CBE01: A coin issued by Uncertain - 1st-mid 3rd century"}{"image_urls":[https://finds.org.uk/images/tgilmore/WMID-D61E06.jpg],"from":1,"to":200,"title":"WMID-D61E06: A coin issued by Uncertain - 1st-mid 3rd century"}{"image_urls":[https://finds.org.uk/images/lwalker/SUSS-6875B6.jpg],"from":1,"to":250,"title":"SUSS-6875B6: A coin issued by Uncertain - 1st-mid 3rd century"}{"image_urls":[https://finds.org.uk/images/voakden/LVPL-F902C5.jpg],"from":1,"to":250,"title":"LVPL-F902C5: A coin issued by Uncertain - 1st-mid 3rd century"}{"image_urls":[https://finds.org.uk/images/preavill/HESH-17D441.jpg],"from":1,"to":120,"title":"HESH-17D441: A coin issued by Uncertain - 1st\/2nd Century AD"}{"image_urls":[https://finds.org.uk/images/tgilmore/WMID-88FE21.jpg],"from":1,"to":200,"title":"WMID-88FE21: A coin issued by Uncertain - 1st-mid 3rd century"}{"image_urls":[https://finds.org.uk/images/gstewart/Great%20Maplestead_SF-17C65B.jpg],"from":1,"to":42,"title":"SF-17C65B: A coin issued by Cunobelin"}{"image_urls":[https://finds.org.uk/images/khindshamp/HAMP-7FD374.jpg],"from":1,"to":200,"title":"HAMP-7FD374: A coin issued by Uncertain - 1st\/2nd Century AD"}{"image_urls":[https://finds.org.uk/images/abrown/KDG_SF-B26EE0.jpg],"from":1,"to":43,"title":"SF-B26EE0: A coin issued by Cunobelin"}{"image_urls":[https://finds.org.uk/images/jplouviez/BUTSF-09E354.JPG],"from":1,"to":42,"title":"SF-09E354: A coin issued by Cunobelin"}{"image_urls":[https://finds.org.uk/images/voakden/LVPL-F8E5E6.jpg],"from":1,"to":250,"title":"LVPL-F8E5E6: A coin issued by Uncertain - 1st-mid 3rd century"}{"image_urls":[https://finds.org.uk/images/hfowler/CAMCD5F58.jpg],"from":1,"to":40,"title":"CAM-CD5F58: A coin issued by Cunobelin"}{"image_urls":[https://finds.org.uk/images/stephaniesmith/SUSS506479.jpg],"from":1,"to":250,"title":"SUSS-506479: A coin issued by Uncertain - 1st-mid 3rd century"}{"image_urls":[https://finds.org.uk/images/stephaniesmith/SUSSA3FB7E.jpg],"from":1,"to":250,"title":"SUSS-A3FB7E: A coin issued by Uncertain - 1st-mid 3rd century"}{"image_urls":[https://finds.org.uk/images/tgilmore/WMID-2B5596a.jpg],"from":1,"to":260,"title":"WMID-2B5596: A coin issued by Uncertain - 1st-mid 3rd century"}{"image_urls":[https://finds.org.uk/images/jplouviez/WFL015SF-207E01.jpg],"from":1,"to":40,"title":"SF-207E01: A coin issued by Cunobelin"}{"image_urls":[https://finds.org.uk/images/stephaniesmith/SUSS2C7EDF.jpg],"from":1,"to":250,"title":"SUSS-2C7EDF: A coin issued by Uncertain - 1st-mid 3rd century"}{"image_urls":[https://finds.org.uk/images/karend1/KENT-1155E6.jpg],"from":1,"to":250,"title":"KENT-1155E6: A coin issued by Uncertain - 1st-mid 3rd century"}{"image_urls":[https://finds.org.uk/images/lwalker/SUSS-5ECD5C.jpg],"from":1,"to":250,"title":"SUSS-5ECD5C: A coin issued by Uncertain - 1st-mid 3rd century"}{"image_urls":[https://finds.org.uk/images/tgilmore/WMID-1B06AB.jpg],"from":1,"to":300,"title":"WMID-1B06AB: A coin issued by Uncertain - 1st-mid 3rd century"}{"image_urls":[https://finds.org.uk/images/stephaniesmith/SUSS-22B994.jpg],"from":1,"to":250,"title":"SUSS-22B994: A coin issued by Uncertain - 1st-mid 3rd century"}{"image_urls":[https://finds.org.uk/images/tgilmore/wmid-4ffb87.jpg],"from":1,"to":250,"title":"WMID-4FFB87: A coin issued by Uncertain - 1st-mid 3rd century"}{"image_urls":[https://finds.org.uk/images/tgilmore/WMID2A67D4.jpg],"from":1,"to":260,"title":"WMID-2A67D4: A coin issued by Uncertain - 1st-mid 3rd century"}{"image_urls":[https://finds.org.uk/images/tgilmore/WMID-1BF666.jpg],"from":1,"to":200,"title":"WMID-1BF666: A coin issued by Uncertain - 1st-mid 3rd century"}{"image_urls":[https://finds.org.uk/images/stephaniesmith/SUSS-F2B03D.jpg],"from":1,"to":250,"title":"SUSS-F2B03D: A coin issued by Uncertain - 1st-mid 3rd century"}{"image_urls":[https://finds.org.uk/images/jplouviez/WFL015SF-205962.jpg],"from":1,"to":40,"title":"SF-205962: A coin issued by Cunobelin"}{"image_urls":[https://finds.org.uk/images/stephaniesmith/SUSS0CB74E.jpg],"from":1,"to":250,"title":"SUSS-0CB74E: A coin issued by Uncertain - 1st-mid 3rd century"}{"image_urls":[https://finds.org.uk/images/voakden/LVPL-AF01D6.jpg],"from":1,"to":260,"title":"LVPL-AF01D6: A coin issued by Uncertain - 1st-mid 3rd century"}{"image_urls":[https://finds.org.uk/images/karend1/KENT-4BD181.jpg],"from":1,"to":250,"title":"KENT-4BD181: A coin issued by Uncertain - 1st-mid 3rd century"}{"image_urls":[https://finds.org.uk/images/khindshamp/HAMP-7FA0B6.jpg],"from":1,"to":200,"title":"HAMP-7FA0B6: A coin issued by Uncertain - 1st\/2nd Century AD"}{"image_urls":[https://finds.org.uk/images/stephaniesmith/SUSS-377B13.jpg],"from":1,"to":250,"title":"SUSS-377B13: A coin issued by Uncertain - 1st-mid 3rd century"}{"image_urls":[https://finds.org.uk/images/tgilmore/WMID7CAF9B.jpg],"from":1,"to":250,"title":"WMID-7CAF9B: A coin issued by Uncertain - 1st-mid 3rd century"}{"image_urls":[https://finds.org.uk/images/voakden/LVPL-6C8196.JPG],"from":1,"to":250,"title":"LVPL-6C8196: A coin issued by Uncertain - 1st-mid 3rd century"}{"image_urls":[https://finds.org.uk/images/tgilmore/WMID7C8A5C.jpg],"from":1,"to":250,"title":"WMID-7C8A5C: A coin issued by Uncertain - 1st-mid 3rd century"}{"image_urls":[https://finds.org.uk/images/voakden/LVPL-027227.jpg],"from":1,"to":260,"title":"LVPL-027227: A coin issued by Uncertain - 1st-mid 3rd century"}{"image_urls":[https://finds.org.uk/images/khinds/Riddle0208dupondius.jpg],"from":1,"to":100,"title":"WILT-9C9827: A coin issued by Domitian"}{"image_urls":[https://finds.org.uk/images/stephaniesmith/SUSS-D0F4C1.jpg],"from":1,"to":250,"title":"SUSS-D0F4C1: A coin issued by Uncertain - 1st-mid 3rd century"}{"image_urls":[https://finds.org.uk/images/tgilmore/WMIDCAED2A.jpg],"from":1,"to":250,"title":"WMID-CAED2A: A coin issued by Uncertain - 1st-mid 3rd century"}{"image_urls":[https://finds.org.uk/images/jplouviez/IslehamSF-98DB73.jpg],"from":1,"to":40,"title":"SF-98DB73: A coin issued by Cunobelin"}{"image_urls":[https://finds.org.uk/images/jplouviez/SNNSF-E46182.JPG],"from":1,"to":40,"title":"SF-E46182: A coin issued by Cunobelin"}{"image_urls":[https://finds.org.uk/images/lwalker/SUSS-20D6A5.jpg],"from":1,"to":250,"title":"SUSS-20D6A5: A coin issued by Uncertain - 1st-mid 3rd century"}{"image_urls":[https://finds.org.uk/images/mforeman/NLM24969.jpg],"from":1,"to":200,"title":"NLM-4522D8: A coin issued by Uncertain - 1st\/2nd Century AD"}{"image_urls":[https://finds.org.uk/images/abrown/DRK_SF-4BB714.jpg],"from":1,"to":42,"title":"SF-4BB714: A coin issued by Cunobelin"}{"image_urls":[https://finds.org.uk/images/ellysg1/SestertiusC12.jpg],"from":1,"to":200,"title":"HAMP-65C175: A coin issued by Uncertain - 1st\/2nd Century AD"}{"image_urls":[https://finds.org.uk/images/stephaniesmith/SUSS351DBF.jpg],"from":1,"to":250,"title":"SUSS-351DBF: A coin issued by Uncertain - 1st-mid 3rd century"}{"image_urls":[https://finds.org.uk/images/abrown/LSY_SF-E01476.jpg],"from":1,"to":42,"title":"SF-E01476: A coin issued by Cunobelin"}{"image_urls":[https://finds.org.uk/images/stephaniesmith/SUSS-37C242.jpg],"from":1,"to":250,"title":"SUSS-37C242: A coin issued by Uncertain - 1st-mid 3rd century"}{"image_urls":[https://finds.org.uk/images/laural/Roman%20coin%20WF%20-%202.jpg],"from":1,"to":200,"title":"BH-88A114: A coin issued by Uncertain - 1st-mid 3rd century"}{"image_urls":[https://finds.org.uk/images/saehoile/SUSS-50E804.jpg],"from":1,"to":199,"title":"SUSS-50E804: A coin issued by Uncertain - 1st\/2nd Century AD"}{"image_urls":[http://numismatics.org/collectionimages/20002049/2001/2001.21.1.rev.width350.jpg],"from":1,"to":200,"title":"Bronze Coin, Ancyra, AD 1 - AD 200. 2001.21.1"}{"image_urls":[https://finds.org.uk/images/lmclean/ESS-C04324.jpg],"from":10,"to":40,"title":"ESS-C04324: A coin issued by Cunobelin"}{"image_urls":[https://finds.org.uk/images/jwatters/IA_coin_12_51_1.jpg],"from":10,"to":40,"title":"BH-BEE6C6: A coin issued by Cunobelin"}{"image_urls":[https://finds.org.uk/images/bmorris/LSH0047.jpg],"from":10,"to":40,"title":"YORYM-F058ED: A coin issued by Cunobelin"}{"image_urls":[https://finds.org.uk/images/jplouviez/COMSF-99DB60.JPG],"from":10,"to":102,"title":"SF-99DB60: A coin issued by Trajan"}{"image_urls":[https://finds.org.uk/images/jwatters/Iron%20Age%20coin%2004%20193%20-%202%20all.jpg],"from":10,"to":40,"title":"BH-8E1728: A coin issued by Cunobelin"}{"image_urls":[https://finds.org.uk/images/jplouviez/FRKSF-5F9FC0.JPG],"from":10,"to":43,"title":"SF-5F9FC0: A coin issued by Cunobelin"}{"image_urls":[https://finds.org.uk/images/margaretb/12-1093.JPG],"from":10,"to":40,"title":"SUR-2C9836: A coin issued by Cunobelin"}{"image_urls":[https://finds.org.uk/images/dwilliams/B13-590.JPG],"from":10,"to":40,"title":"SUR-A6E948: A coin issued by Verica"}{"image_urls":[https://finds.org.uk/images/margaretb/141492.JPG],"from":10,"to":40,"title":"SUR-23E6F2: A coin with an unrecorded\/uncertain issuer."}{"image_urls":[https://finds.org.uk/images/lmclean/1a%20ESS-BC4133.jpg],"from":10,"to":40,"title":"ESS-BC4133: A coin issued by Cunobelin"}{"image_urls":[https://finds.org.uk/images/maritime/521StayerCoinTktP.jpg],"from":10,"to":40,"title":"BERK-707625: A coin issued by Cunobelin"}{"image_urls":[https://finds.org.uk/images/smatthews/CAM-8124C1%20coin.jpg],"from":10,"to":40,"title":"CAM-8124C1: A coin issued by Cunobelin"}{"image_urls":[https://finds.org.uk/images/dwilliams/15880.JPG],"from":10,"to":40,"title":"SUR-3FAE33: A coin issued by Verica"}{"image_urls":[https://finds.org.uk/images/jplouviez/LittleWilbrahamSF-81D101.jpg],"from":10,"to":43,"title":"SF-81D101: A coin issued by Cunobelin"}{"image_urls":[https://finds.org.uk/images/rflook/PAS%2024-01-1011%20004.jpg],"from":10,"to":40,"title":"GAT-9CE843: A coin issued by Cunobelin"}{"image_urls":[https://finds.org.uk/images/dboughton/LVMDMLA41D34.jpg],"from":10,"to":40,"title":"LANCUM-A41D34: A coin issued by Cunobelin"}{"image_urls":[https://finds.org.uk/images/reggomez/Qtr%20Stater%20Final.jpg],"from":10,"to":40,"title":"LANCUM-8DA201: A coin issued by Cunobelin"}{"image_urls":[https://finds.org.uk/images/dwilliams/15881.JPG],"from":10,"to":40,"title":"SUR-3FD4D0: A coin issued by Epaticcus"}{"image_urls":[https://finds.org.uk/images/abrown/BKY_SF-335D18.jpg],"from":10,"to":43,"title":"SF-335D18: A coin issued by Cunobelin"}{"image_urls":[https://finds.org.uk/images/cmcdonald/Sharp%20LIA%20bronxe%20unit%20cunobelin%20jupiter.jpg],"from":10,"to":40,"title":"ESS-D13B82: A coin issued by Cunobelin"}{"image_urls":[https://finds.org.uk/images/mdlmarshall/6157%20e.jpg],"from":10,"to":20,"title":"ESS-6FD5E4: A coin issued by Cunobelin"}{"image_urls":[https://finds.org.uk/images/wscott/C63B07.JPG],"from":10,"to":40,"title":"LEIC-C63B07: A coin issued by Cunobelin"}{"image_urls":[https://finds.org.uk/images/jwatters/IA_coin_14_107_3.jpg],"from":10,"to":40,"title":"BH-F50A08: A coin issued by Cunobelin"}{"image_urls":[https://finds.org.uk/images/cmcdonald/Sharp%20LIA%20bronxe%20unit%20cunobelin%20lion.jpg],"from":10,"to":40,"title":"ESS-D16354: A coin issued by Cunobelin"}{"image_urls":[https://finds.org.uk/images/jwatters/IA_coin_14_100_1.jpg],"from":10,"to":40,"title":"BH-F61519: A coin issued by Cunobelin"}{"image_urls":[https://finds.org.uk/images/jplouviez/WFLSF-BD9583.jpg],"from":10,"to":40,"title":"SF-BD9583: A coin issued by Cunobelin"}{"image_urls":[https://finds.org.uk/images/dwilliams/07.604.JPG],"from":10,"to":40,"title":"SUR-C5D9A3: A coin issued by Cunobelin"}{"image_urls":[https://finds.org.uk/images/jwatters/Ia%20coin%2009%2025%20-%205b.jpg],"from":10,"to":40,"title":"BH-BA7F22: A coin issued by Cunobelin"}{"image_urls":[https://finds.org.uk/images/lmclean/1%20ESS-BC70A5%20quarter%20stater%20cunobelin.jpg],"from":10,"to":40,"title":"ESS-BC70A5: A coin issued by Cunobelin"}{"image_urls":[https://finds.org.uk/images/jwatters/IA%20coin%20B2471%20-%206a.jpg],"from":10,"to":20,"title":"BH-B82851: A coin issued by Cunobelin"}{"image_urls":[https://finds.org.uk/images/lmclean/ESS-59B001.jpg],"from":10,"to":41,"title":"ESS-59B001: A coin issued by Cunobelin"}{"image_urls":[https://finds.org.uk/images/lmclean/1d%20ESS-C9AC01.jpg],"from":10,"to":20,"title":"ESS-C9AC01: A coin issued by Cunobelin"}{"image_urls":[https://finds.org.uk/images/hfowler/CAM-BCAF46.jpg],"from":10,"to":40,"title":"CAM-BCAF46: A coin issued by Cunobelin"}{"image_urls":[https://finds.org.uk/images/jcassidy/NARC-BC19E3b.jpg],"from":10,"to":40,"title":"NARC-BC19E3: A coin issued by Cunobelin"}{"image_urls":[https://finds.org.uk/images/abyard/2013144.jpg],"from":10,"to":40,"title":"BERK-3308A2: A coin issued by Verica"}{"image_urls":[https://finds.org.uk/images/lmclean/1b%20ESS-0A5107%20Iron%20Age%20coin%20stater%20of%20Cunobelin.jpg],"from":10,"to":20,"title":"ESS-0A5107: A coin issued by Cunobelin"}{"image_urls":[https://finds.org.uk/images/gburr/DSCN3641.JPG],"from":10,"to":40,"title":"KENT-EEC8F1: A coin issued by Cunobelin"}{"image_urls":[https://finds.org.uk/images/jwatters/Iron%20Age%20coin%200464-176.jpg],"from":10,"to":40,"title":"BH-A135D8: A coin issued by Cunobelin"}{"image_urls":[https://finds.org.uk/images/abrown/BSM%20SF-3F7F07.jpg],"from":10,"to":20,"title":"SF-3F7F07: A coin issued by Cunobelin"}{"image_urls":[https://finds.org.uk/images/dunvant/5DSCN0257.JPG],"from":10,"to":40,"title":"BUC-5EBE59: A coin issued by Cunobelin"}{"image_urls":[https://finds.org.uk/images/jplouviez/HTCSF-4EA2B2.JPG],"from":10,"to":40,"title":"SF-4EA2B2: A coin issued by Cunobelin"}{"image_urls":[https://finds.org.uk/images/elburnett/SOM-A0C097.JPG],"from":10,"to":40,"title":"SOM-A0C097: A coin issued by Cunobelin"}{"image_urls":[https://finds.org.uk/images/hfowler/CAM-2204F6.jpg],"from":10,"to":40,"title":"CAM-2204F6: A coin issued by Cunobelin"}{"image_urls":[https://finds.org.uk/images/eloise77/Iron%20Age.jpg],"from":10,"to":40,"title":"ESS-0684C6: A coin issued by Cunobelin"}{"image_urls":[http://numismatics.org/collectionimages/19001949/1944/1944.100.83096.rev.width350.jpg],"from":10,"to":38,"title":"Bronze Coin, Ecbatana, AD 10 - AD 38. 1944.100.83096"}{"image_urls":[http://numismatics.org/collectionimages/19001949/1944/1944.100.83288.rev.width350.jpg],"from":10,"to":38,"title":"Silver Drachm, Ecbatana, AD 10 - AD 38. 1944.100.83288"}{"image_urls":[http://numismatics.org/collectionimages/19501999/1973/1973.56.1656.rev.width350.jpg],"from":10,"to":38,"title":"Silver Drachm, Ecbatana, AD 10 - AD 38. 1973.56.1656"}{"image_urls":[http://numismatics.org/collectionimages/19001949/1944/1944.100.83093.rev.width350.jpg],"from":10,"to":38,"title":"Bronze Coin, Ecbatana, AD 10 - AD 38. 1944.100.83093"}{"image_urls":[http://numismatics.org/collectionimages/19001949/1944/1944.100.83051.rev.width350.jpg],"from":10,"to":38,"title":"Bronze Coin, Ecbatana, AD 10 - AD 38. 1944.100.83051"}{"image_urls":[http://numismatics.org/collectionimages/19001949/1944/1944.100.82997.rev.width350.jpg],"from":10,"to":11,"title":"Silver Tetradrachm, Seleuceia ad Tigrim, AD 10 - AD 11. 1944.100.82997"}{"image_urls":[http://numismatics.org/collectionimages/19001949/1944/1944.100.83066.rev.width350.jpg],"from":10,"to":38,"title":"Silver Drachm, Ecbatana, AD 10 - AD 38. 1944.100.83066"}{"image_urls":[http://numismatics.org/collectionimages/19001949/1944/1944.100.83087.rev.width350.jpg],"from":10,"to":38,"title":"Bronze Coin, Ecbatana, AD 10 - AD 38. 1944.100.83087"}{"image_urls":[http://numismatics.org/collectionimages/19001949/1944/1944.100.83048.rev.width350.jpg],"from":10,"to":38,"title":"Bronze Coin, Ecbatana, AD 10 - AD 38. 1944.100.83048"}{"image_urls":[http://numismatics.org/collectionimages/19001949/1944/1944.100.83081.rev.width350.jpg],"from":10,"to":38,"title":"Bronze Coin, Ecbatana, AD 10 - AD 38. 1944.100.83081"}{"image_urls":[http://numismatics.org/collectionimages/19001949/1944/1944.100.83075.rev.width350.jpg],"from":10,"to":38,"title":"Bronze Coin, Ecbatana, AD 10 - AD 38. 1944.100.83075"}{"image_urls":[http://numismatics.org/collectionimages/19001949/1923/1923.150.401.rev.width350.jpg],"from":10,"to":38,"title":"Silver Drachm, Nisa Mithradatkart, AD 10 - AD 38. 1923.150.401"}{"image_urls":[http://numismatics.org/collectionimages/19001949/1944/1944.100.83100.rev.width350.jpg],"from":10,"to":38,"title":"Bronze Coin, Ecbatana, AD 10 - AD 38. 1944.100.83100"}{"image_urls":[http://numismatics.org/collectionimages/19001949/1944/1944.100.83090.rev.width350.jpg],"from":10,"to":38,"title":"Bronze Coin, Ecbatana, AD 10 - AD 38. 1944.100.83090"}{"image_urls":[http://numismatics.org/collectionimages/19001949/1944/1944.100.83099.rev.width350.jpg],"from":10,"to":38,"title":"Bronze Coin, Ecbatana, AD 10 - AD 38. 1944.100.83099"}{"image_urls":[http://numismatics.org/collectionimages/19501999/1973/1973.56.1662.rev.width350.jpg],"from":10,"to":38,"title":"Bronze Coin, Ecbatana, AD 10 - AD 38. 1973.56.1662"}{"image_urls":[http://numismatics.org/collectionimages/19001949/1944/1944.100.83102.rev.width350.jpg],"from":10,"to":38,"title":"Bronze Coin, Ecbatana, AD 10 - AD 38. 1944.100.83102"}{"image_urls":[http://numismatics.org/collectionimages/19001949/1944/1944.100.83024.rev.width350.jpg],"from":10,"to":38,"title":"Bronze Coin, Ecbatana, AD 10 - AD 38. 1944.100.83024"}{"image_urls":[http://numismatics.org/collectionimages/19001949/1944/1944.100.68884.rev.width350.jpg],"from":10,"to":14,"title":"RIC I (second edition) Augustus 160. 1944.100.68884"}{"image_urls":[http://numismatics.org/collectionimages/00001899/0000/0000.999.52975.rev.width350.jpg],"from":10,"to":38,"title":"Silver Drachm, Ecbatana, AD 10 - AD 38. 0000.999.52975"}{"image_urls":[http://numismatics.org/collectionimages/19501999/1973/1973.56.1667.rev.width350.jpg],"from":10,"to":38,"title":"Bronze Coin, Ecbatana, AD 10 - AD 38. 1973.56.1667"}{"image_urls":[http://numismatics.org/collectionimages/19501999/1977/1977.158.793.rev.width350.jpg],"from":10,"to":38,"title":"Silver Drachm, Ecbatana, AD 10 - AD 38. 1977.158.793"}{"image_urls":[http://numismatics.org/collectionimages/19001949/1944/1944.100.83083.rev.width350.jpg],"from":10,"to":38,"title":"Bronze Coin, Ecbatana, AD 10 - AD 38. 1944.100.83083"}{"image_urls":[http://numismatics.org/collectionimages/19001949/1944/1944.100.83077.rev.width350.jpg],"from":10,"to":38,"title":"Bronze Coin, Ecbatana, AD 10 - AD 38. 1944.100.83077"}{"image_urls":[http://numismatics.org/collectionimages/19501999/1973/1973.56.1661.rev.width350.jpg],"from":10,"to":38,"title":"Bronze Coin, Ecbatana, AD 10 - AD 38. 1973.56.1661"}{"image_urls":[http://numismatics.org/collectionimages/19501999/1973/1973.56.1655.rev.width350.jpg],"from":10,"to":38,"title":"Bronze Coin, Ecbatana, AD 10 - AD 38. 1973.56.1655"}{"image_urls":[http://numismatics.org/collectionimages/19501999/1977/1977.158.798.rev.width350.jpg],"from":10,"to":38,"title":"Silver Drachm, Ecbatana, AD 10 - AD 38. 1977.158.798"}{"image_urls":[http://numismatics.org/collectionimages/00001899/0000/0000.999.52978.rev.width350.jpg],"from":10,"to":38,"title":"Bronze Coin, Ecbatana, AD 10 - AD 38. 0000.999.52978"}{"image_urls":[http://numismatics.org/collectionimages/19001949/1944/1944.100.83034.rev.width350.jpg],"from":10,"to":38,"title":"Bronze Coin, Ecbatana, AD 10 - AD 38. 1944.100.83034"}{"image_urls":[http://numismatics.org/collectionimages/19001949/1944/1944.100.83028.rev.width350.jpg],"from":10,"to":38,"title":"Bronze Coin, Ecbatana, AD 10 - AD 38. 1944.100.83028"}{"image_urls":[http://numismatics.org/collectionimages/00001899/0000/0000.999.52976.rev.width350.jpg],"from":10,"to":38,"title":"Silver Drachm, Ecbatana, AD 10 - AD 38. 0000.999.52976"}{"image_urls":[http://numismatics.org/collectionimages/19501999/1973/1973.56.1668.rev.width350.jpg],"from":10,"to":38,"title":"Bronze Coin, Ecbatana, AD 10 - AD 38. 1973.56.1668"}{"image_urls":[http://numismatics.org/collectionimages/19001949/1944/1944.100.39272.rev.width350.jpg],"from":10,"to":11,"title":"RIC I (second edition) Augustus 469. 1944.100.39272"}{"image_urls":[http://numismatics.org/collectionimages/19001949/1944/1944.100.83042.rev.width350.jpg],"from":10,"to":38,"title":"Silver Drachm, Ecbatana, AD 10 - AD 38. 1944.100.83042"}{"image_urls":[http://numismatics.org/collectionimages/19501999/1970/1970.156.730.rev.width350.jpg],"from":10,"to":38,"title":"Silver Drachm, Ecbatana, AD 10 - AD 38. 1970.156.730"}{"image_urls":[http://numismatics.org/collectionimages/19001949/1944/1944.100.83036.rev.width350.jpg],"from":10,"to":38,"title":"Bronze Coin, Ecbatana, AD 10 - AD 38. 1944.100.83036"}{"image_urls":[http://numismatics.org/collectionimages/19001949/1944/1944.100.83063.rev.width350.jpg],"from":10,"to":38,"title":"Bronze Coin, Ecbatana, AD 10 - AD 38. 1944.100.83063"}{"image_urls":[http://numismatics.org/collectionimages/19001949/1944/1944.100.83045.rev.width350.jpg],"from":10,"to":38,"title":"Bronze Coin, Ecbatana, AD 10 - AD 38. 1944.100.83045"}{"image_urls":[http://numismatics.org/collectionimages/19001949/1944/1944.100.83039.rev.width350.jpg],"from":10,"to":38,"title":"Silver Drachm, Ecbatana, AD 10 - AD 38. 1944.100.83039"}{"image_urls":[http://numismatics.org/collectionimages/19001949/1944/1944.100.83060.rev.width350.jpg],"from":10,"to":38,"title":"Bronze Coin, Ecbatana, AD 10 - AD 38. 1944.100.83060"}{"image_urls":[http://numismatics.org/collectionimages/19001949/1944/1944.100.83054.rev.width350.jpg],"from":10,"to":38,"title":"Bronze Coin, Ecbatana, AD 10 - AD 38. 1944.100.83054"}{"image_urls":[http://numismatics.org/collectionimages/19001949/1941/1941.131.1123.rev.width350.jpg],"from":10,"to":38,"title":"Silver Drachm, Ecbatana, AD 10 - AD 38. 1941.131.1123"}{"image_urls":[http://numismatics.org/collectionimages/19001949/1947/1947.97.612.rev.width350.jpg],"from":10,"to":38,"title":"Bronze Coin, Ecbatana, AD 10 - AD 38. 1947.97.612"}{"image_urls":[http://numismatics.org/collectionimages/19001949/1944/1944.100.83021.rev.width350.jpg],"from":10,"to":38,"title":"Silver Drachm, Ecbatana, AD 10 - AD 38. 1944.100.83021"}{"image_urls":[http://numismatics.org/collectionimages/19001949/1944/1944.100.83089.rev.width350.jpg],"from":10,"to":38,"title":"Bronze Coin, Ecbatana, AD 10 - AD 38. 1944.100.83089"}{"image_urls":[http://numismatics.org/collectionimages/19001949/1944/1944.100.83027.rev.width350.jpg],"from":10,"to":38,"title":"Bronze Coin, Ecbatana, AD 10 - AD 38. 1944.100.83027"}{"image_urls":[http://numismatics.org/collectionimages/19001949/1944/1944.100.83095.rev.width350.jpg],"from":10,"to":38,"title":"Bronze Coin, Ecbatana, AD 10 - AD 38. 1944.100.83095"}{"image_urls":[http://numismatics.org/collectionimages/19001949/1944/1944.100.83080.rev.width350.jpg],"from":10,"to":38,"title":"Bronze Coin, Ecbatana, AD 10 - AD 38. 1944.100.83080"}{"image_urls":[http://numismatics.org/collectionimages/19001949/1944/1944.100.83085.rev.width350.jpg],"from":10,"to":38,"title":"Bronze Coin, Ecbatana, AD 10 - AD 38. 1944.100.83085"}{"image_urls":[http://numismatics.org/collectionimages/19501999/1973/1973.56.1663.rev.width350.jpg],"from":10,"to":38,"title":"Silver Drachm, Ecbatana, AD 10 - AD 38. 1973.56.1663"}{"image_urls":[http://numismatics.org/collectionimages/19001949/1944/1944.100.83101.rev.width350.jpg],"from":10,"to":38,"title":"Bronze Coin, Ecbatana, AD 10 - AD 38. 1944.100.83101"}{"image_urls":[http://numismatics.org/collectionimages/19001949/1944/1944.100.83023.rev.width350.jpg],"from":10,"to":38,"title":"Bronze Coin, Ecbatana, AD 10 - AD 38. 1944.100.83023"}{"image_urls":[http://numismatics.org/collectionimages/19501999/1973/1973.56.1684.rev.width350.jpg],"from":10,"to":38,"title":"Bronze Coin, Ecbatana, AD 10 - AD 38. 1973.56.1684"}{"image_urls":[http://numismatics.org/collectionimages/19001949/1944/1944.100.83091.rev.width350.jpg],"from":10,"to":38,"title":"Bronze Coin, Ecbatana, AD 10 - AD 38. 1944.100.83091"}{"image_urls":[http://numismatics.org/collectionimages/19001949/1944/1944.100.83088.rev.width350.jpg],"from":10,"to":38,"title":"Bronze Coin, Ecbatana, AD 10 - AD 38. 1944.100.83088"}{"image_urls":[http://numismatics.org/collectionimages/19501999/1973/1973.56.1666.rev.width350.jpg],"from":10,"to":38,"title":"Bronze Coin, Ecbatana, AD 10 - AD 38. 1973.56.1666"}{"image_urls":[http://numismatics.org/collectionimages/19001949/1940/1940.169.7.rev.width350.jpg],"from":10,"to":38,"title":"Bronze Coin, Ecbatana, AD 10 - AD 38. 1940.169.7"}{"image_urls":[http://numismatics.org/collectionimages/00001899/0000/0000.999.52980.rev.width350.jpg],"from":10,"to":38,"title":"Silver Drachm, Ecbatana, AD 10 - AD 38. 0000.999.52980"}{"image_urls":[http://numismatics.org/collectionimages/19501999/1973/1973.56.1664.rev.width350.jpg],"from":10,"to":38,"title":"Bronze Coin, Ecbatana, AD 10 - AD 38. 1973.56.1664"}{"image_urls":[http://numismatics.org/collectionimages/19001949/1944/1944.100.83059.rev.width350.jpg],"from":10,"to":38,"title":"Bronze Coin, Ecbatana, AD 10 - AD 38. 1944.100.83059"}{"image_urls":[http://numismatics.org/collectionimages/19001949/1944/1944.100.83086.rev.width350.jpg],"from":10,"to":38,"title":"Bronze Coin, Ecbatana, AD 10 - AD 38. 1944.100.83086"}{"image_urls":[http://numismatics.org/collectionimages/19001949/1944/1944.100.83050.rev.width350.jpg],"from":10,"to":38,"title":"Bronze Coin, Ecbatana, AD 10 - AD 38. 1944.100.83050"}{"image_urls":[http://numismatics.org/collectionimages/19001949/1944/1944.100.83044.rev.width350.jpg],"from":10,"to":38,"title":"Silver Drachm, Ecbatana, AD 10 - AD 38. 1944.100.83044"}{"image_urls":[http://numismatics.org/collectionimages/19001949/1944/1944.100.83065.rev.width350.jpg],"from":10,"to":38,"title":"Bronze Coin, Ecbatana, AD 10 - AD 38. 1944.100.83065"}{"image_urls":[http://numismatics.org/collectionimages/19001949/1944/1944.100.83094.rev.width350.jpg],"from":10,"to":38,"title":"Bronze Coin, Ecbatana, AD 10 - AD 38. 1944.100.83094"}{"image_urls":[http://numismatics.org/collectionimages/00001899/0000/0000.999.52974.rev.width350.jpg],"from":10,"to":38,"title":"Silver Drachm, Ecbatana, AD 10 - AD 38. 0000.999.52974"}{"image_urls":[http://numismatics.org/collectionimages/19001949/1944/1944.100.83104.rev.width350.jpg],"from":10,"to":38,"title":"Bronze Coin, Ecbatana, AD 10 - AD 38. 1944.100.83104"}{"image_urls":[http://numismatics.org/collectionimages/20002049/2000/2000.7.133.rev.width350.jpg],"from":10,"to":38,"title":"Silver drachm, Ecbatana, AD 10 - AD 38. 2000.7.133"}{"image_urls":[http://numismatics.org/collectionimages/19001949/1944/1944.100.83073.rev.width350.jpg],"from":10,"to":38,"title":"Silver Drachm, Ecbatana, AD 10 - AD 38. 1944.100.83073"}{"image_urls":[http://numismatics.org/collectionimages/19001949/1944/1944.100.83067.rev.width350.jpg],"from":10,"to":38,"title":"Silver Drachm, Ecbatana, AD 10 - AD 38. 1944.100.83067"}{"image_urls":[http://numismatics.org/collectionimages/19501999/1973/1973.56.1654.rev.width350.jpg],"from":10,"to":38,"title":"Silver Drachm, Ecbatana, AD 10 - AD 38. 1973.56.1654"}{"image_urls":[http://numismatics.org/collectionimages/19001949/1944/1944.100.83049.rev.width350.jpg],"from":10,"to":38,"title":"Bronze Coin, Ecbatana, AD 10 - AD 38. 1944.100.83049"}{"image_urls":[http://numismatics.org/collectionimages/19001949/1944/1944.100.83053.rev.width350.jpg],"from":10,"to":38,"title":"Bronze Coin, Ecbatana, AD 10 - AD 38. 1944.100.83053"}{"image_urls":[http://numismatics.org/collectionimages/19001949/1944/1944.100.83068.rev.width350.jpg],"from":10,"to":38,"title":"Silver Drachm, Ecbatana, AD 10 - AD 38. 1944.100.83068"}{"image_urls":[http://numismatics.org/collectionimages/19001949/1944/1944.100.83026.rev.width350.jpg],"from":10,"to":38,"title":"Bronze Coin, Ecbatana, AD 10 - AD 38. 1944.100.83026"}{"image_urls":[http://numismatics.org/collectionimages/19001949/1944/1944.100.83098.rev.width350.jpg],"from":10,"to":38,"title":"Bronze Coin, Ecbatana, AD 10 - AD 38. 1944.100.83098"}{"image_urls":[http://numismatics.org/collectionimages/19001949/1944/1944.100.83062.rev.width350.jpg],"from":10,"to":38,"title":"Bronze Coin, Ecbatana, AD 10 - AD 38. 1944.100.83062"}{"image_urls":[http://numismatics.org/collectionimages/19001949/1944/1944.100.83056.rev.width350.jpg],"from":10,"to":38,"title":"Bronze Coin, Ecbatana, AD 10 - AD 38. 1944.100.83056"}{"image_urls":[http://numismatics.org/collectionimages/19001949/1944/1944.100.39268.rev.width350.jpg],"from":10,"to":14,"title":"Bronze Semis of Augustus, Lugdunum, AD 10 - AD 14. 1944.100.39268"}{"image_urls":[http://numismatics.org/collectionimages/19001949/1944/1944.100.83038.rev.width350.jpg],"from":10,"to":38,"title":"Silver Drachm, Ecbatana, AD 10 - AD 38. 1944.100.83038"}{"image_urls":[http://numismatics.org/collectionimages/19501999/1973/1973.56.1658.rev.width350.jpg],"from":10,"to":38,"title":"Silver Drachm, Ecbatana, AD 10 - AD 38. 1973.56.1658"}{"image_urls":[http://numismatics.org/collectionimages/19001949/1944/1944.100.83071.rev.width350.jpg],"from":10,"to":38,"title":"Silver Drachm, Ecbatana, AD 10 - AD 38. 1944.100.83071"}{"image_urls":[http://numismatics.org/collectionimages/19001949/1944/1944.100.83128.rev.width350.jpg],"from":10,"to":38,"title":"Silver Drachm, Ecbatana, AD 10 - AD 38. 1944.100.83128"}{"image_urls":[http://numismatics.org/collectionimages/19001949/1944/1944.100.83041.rev.width350.jpg],"from":10,"to":38,"title":"Silver Drachm, Ecbatana, AD 10 - AD 38. 1944.100.83041"}{"image_urls":[http://numismatics.org/collectionimages/19001949/1944/1944.100.83035.rev.width350.jpg],"from":10,"to":38,"title":"Bronze Coin, Ecbatana, AD 10 - AD 38. 1944.100.83035"}{"image_urls":[http://numismatics.org/collectionimages/19501999/1993/1993.45.11.rev.width350.jpg],"from":10,"to":38,"title":"Silver Drachm, Ecbatana, AD 10 - AD 38. 1993.45.11"}{"image_urls":[http://numismatics.org/collectionimages/00001899/0000/0000.999.52977.rev.width350.jpg],"from":10,"to":38,"title":"Silver Drachm, Ecbatana, AD 10 - AD 38. 0000.999.52977"}{"image_urls":[http://numismatics.org/collectionimages/19001949/1944/1944.100.83032.rev.width350.jpg],"from":10,"to":38,"title":"Bronze Coin, Ecbatana, AD 10 - AD 38. 1944.100.83032"}{"image_urls":[http://numismatics.org/collectionimages/19001949/1944/1944.100.83047.rev.width350.jpg],"from":10,"to":38,"title":"Bronze Coin, Ecbatana, AD 10 - AD 38. 1944.100.83047"}{"image_urls":[http://numismatics.org/collectionimages/19001949/1944/1944.100.83057.rev.width350.jpg],"from":10,"to":38,"title":"Bronze Coin, Ecbatana, AD 10 - AD 38. 1944.100.83057"}{"image_urls":[http://numismatics.org/collectionimages/19001949/1944/1944.100.83201.rev.width350.jpg],"from":10,"to":38,"title":"Bronze Coin, Ecbatana, AD 10 - AD 38. 1944.100.83201"}{"image_urls":[http://numismatics.org/collectionimages/00001899/0000/0000.999.52972.rev.width350.jpg],"from":10,"to":38,"title":"Bronze Coin, Ecbatana, AD 10 - AD 38. 0000.999.52972"}{"image_urls":[http://numismatics.org/collectionimages/19501999/1973/1973.56.1670.rev.width350.jpg],"from":10,"to":38,"title":"Bronze Coin, Ecbatana, AD 10 - AD 38. 1973.56.1670"}{"image_urls":[http://numismatics.org/collectionimages/19001949/1944/1944.100.83092.rev.width350.jpg],"from":10,"to":38,"title":"Bronze Coin, Ecbatana, AD 10 - AD 38. 1944.100.83092"}{"image_urls":[http://numismatics.org/collectionimages/19001949/1944/1944.100.68878.rev.width350.jpg],"from":10,"to":14,"title":"RIC I (second edition) Augustus 159. 1944.100.68878"}{"image_urls":[http://numismatics.org/collectionimages/19001949/1944/1944.100.83020.rev.width350.jpg],"from":10,"to":38,"title":"Silver Drachm, Ecbatana, AD 10 - AD 38. 1944.100.83020"}{"image_urls":[http://numismatics.org/collectionimages/19001949/1944/1944.100.83029.rev.width350.jpg],"from":10,"to":38,"title":"Bronze Coin, Ecbatana, AD 10 - AD 38. 1944.100.83029"}{"image_urls":[http://numismatics.org/collectionimages/19001949/1919/1919.233.4.rev.width350.jpg],"from":10,"to":14,"title":"RIC I (second edition) Augustus 160. 1919.233.4"}{"image_urls":[http://numismatics.org/collectionimages/19001949/1944/1944.100.83043.rev.width350.jpg],"from":10,"to":38,"title":"Silver Drachm, Ecbatana, AD 10 - AD 38. 1944.100.83043"}{"image_urls":[http://numismatics.org/collectionimages/19001949/1944/1944.100.83070.rev.width350.jpg],"from":10,"to":38,"title":"Silver Drachm, Ecbatana, AD 10 - AD 38. 1944.100.83070"}{"image_urls":[http://numismatics.org/collectionimages/20002049/2015/2015.12.3.rev.width350.jpg],"from":10,"to":14,"title":"RIC I (second edition) Augustus 159. 2015.12.3"}{"image_urls":[http://numismatics.org/collectionimages/19001949/1944/1944.100.83064.rev.width350.jpg],"from":10,"to":38,"title":"Bronze Coin, Ecbatana, AD 10 - AD 38. 1944.100.83064"}{"image_urls":[http://numismatics.org/collectionimages/19501999/1974/1974.52.28.rev.width350.jpg],"from":10,"to":38,"title":"Bronze Coin, Ecbatana, AD 10 - AD 38. 1974.52.28"}{"image_urls":[http://numismatics.org/collectionimages/19001949/1944/1944.100.83022.rev.width350.jpg],"from":10,"to":38,"title":"Bronze Coin, Ecbatana, AD 10 - AD 38. 1944.100.83022"}{"image_urls":[http://numismatics.org/collectionimages/19001949/1944/1944.100.83058.rev.width350.jpg],"from":10,"to":38,"title":"Bronze Coin, Ecbatana, AD 10 - AD 38. 1944.100.83058"}{"image_urls":[http://numismatics.org/collectionimages/19501999/1973/1973.56.1657.rev.width350.jpg],"from":10,"to":38,"title":"Bronze Coin, Ecbatana, AD 10 - AD 38. 1973.56.1657"}{"image_urls":[http://numismatics.org/collectionimages/19001949/1944/1944.100.83061.rev.width350.jpg],"from":10,"to":38,"title":"Bronze Coin, Ecbatana, AD 10 - AD 38. 1944.100.83061"}{"image_urls":[http://numismatics.org/collectionimages/19001949/1944/1944.100.39273.rev.width350.jpg],"from":10,"to":11,"title":"RIC I (second edition) Augustus 469. 1944.100.39273"}{"image_urls":[http://numismatics.org/collectionimages/19001949/1944/1944.100.83076.rev.width350.jpg],"from":10,"to":38,"title":"Bronze Coin, Ecbatana, AD 10 - AD 38. 1944.100.83076"}{"image_urls":[http://numismatics.org/collectionimages/19501999/1959/1959.123.33.rev.width350.jpg],"from":10,"to":38,"title":"Bronze Coin, Ecbatana, AD 10 - AD 38. 1959.123.33"}{"image_urls":[http://numismatics.org/collectionimages/19001949/1944/1944.100.83289.rev.width350.jpg],"from":10,"to":38,"title":"Silver Drachm, Ecbatana, AD 10 - AD 38. 1944.100.83289"}{"image_urls":[http://numismatics.org/collectionimages/19001949/1944/1944.100.83175.rev.width350.jpg],"from":10,"to":38,"title":"Silver Drachm, Nisa Mithradatkart, AD 10 - AD 38. 1944.100.83175"}{"image_urls":[http://numismatics.org/collectionimages/19001949/1944/1944.100.83082.rev.width350.jpg],"from":10,"to":38,"title":"Bronze Coin, Ecbatana, AD 10 - AD 38. 1944.100.83082"}{"image_urls":[http://numismatics.org/collectionimages/19001949/1944/1944.100.83097.rev.width350.jpg],"from":10,"to":38,"title":"Bronze Coin, Ecbatana, AD 10 - AD 38. 1944.100.83097"}{"image_urls":[http://numismatics.org/collectionimages/19001949/1944/1944.100.83040.rev.width350.jpg],"from":10,"to":38,"title":"Silver Drachm, Ecbatana, AD 10 - AD 38. 1944.100.83040"}{"image_urls":[http://numismatics.org/collectionimages/19501999/1973/1973.56.1660.rev.width350.jpg],"from":10,"to":38,"title":"Bronze Coin, Ecbatana, AD 10 - AD 38. 1973.56.1660"}{"image_urls":[http://numismatics.org/collectionimages/19001949/1944/1944.100.83055.rev.width350.jpg],"from":10,"to":38,"title":"Bronze Coin, Ecbatana, AD 10 - AD 38. 1944.100.83055"}{"image_urls":[http://numismatics.org/collectionimages/19501999/1973/1973.56.1669.rev.width350.jpg],"from":10,"to":38,"title":"Bronze Coin, Ecbatana, AD 10 - AD 38. 1973.56.1669"}{"image_urls":[http://numismatics.org/collectionimages/19001949/1944/1944.100.83079.rev.width350.jpg],"from":10,"to":38,"title":"Bronze Coin, Ecbatana, AD 10 - AD 38. 1944.100.83079"}{"image_urls":[http://numismatics.org/collectionimages/19001949/1944/1944.100.83151.rev.width350.jpg],"from":10,"to":38,"title":"Silver Drachm, Ecbatana, AD 10 - AD 38. 1944.100.83151"}{"image_urls":[http://numismatics.org/collectionimages/19001949/1944/1944.100.83202.rev.width350.jpg],"from":10,"to":38,"title":"Bronze Coin, Ecbatana, AD 10 - AD 38. 1944.100.83202"}{"image_urls":[http://numismatics.org/collectionimages/19001949/1944/1944.100.83046.rev.width350.jpg],"from":10,"to":38,"title":"Bronze Coin, Ecbatana, AD 10 - AD 38. 1944.100.83046"}{"image_urls":[http://numismatics.org/collectionimages/19001949/1944/1944.100.68885.rev.width350.jpg],"from":10,"to":14,"title":"RIC I (second edition) Augustus 159. 1944.100.68885"}{"image_urls":[http://numismatics.org/collectionimages/19501999/1956/1956.163.1624.rev.width350.jpg],"from":10,"to":38,"title":"Silver Drachm, Ecbatana, AD 10 - AD 38. 1956.163.1624"}{"image_urls":[http://numismatics.org/collectionimages/19001949/1944/1944.100.83103.rev.width350.jpg],"from":10,"to":38,"title":"Bronze Coin, Ecbatana, AD 10 - AD 38. 1944.100.83103"}{"image_urls":[http://numismatics.org/collectionimages/19001949/1944/1944.100.83052.rev.width350.jpg],"from":10,"to":38,"title":"Bronze Coin, Ecbatana, AD 10 - AD 38. 1944.100.83052"}{"image_urls":[http://numismatics.org/collectionimages/19001949/1944/1944.100.82998.rev.width350.jpg],"from":10,"to":11,"title":"Silver Tetradrachm, Seleuceia ad Tigrim, AD 10 - AD 11. 1944.100.82998"}{"image_urls":[http://numismatics.org/collectionimages/00001899/0000/0000.999.52973.rev.width350.jpg],"from":10,"to":38,"title":"Silver Drachm, Ecbatana, AD 10 - AD 38. 0000.999.52973"}{"image_urls":[http://numismatics.org/collectionimages/19001949/1932/1932.999.239.rev.width350.jpg],"from":10,"to":11,"title":"RIC I (second edition) Augustus 469. 1932.999.239"}{"image_urls":[http://numismatics.org/collectionimages/19001949/1944/1944.100.83010.rev.width350.jpg],"from":10,"to":38,"title":"Silver Tetradrachm, Seleuceia ad Tigrim, AD 10 - AD 38. 1944.100.83010"}{"image_urls":[http://numismatics.org/collectionimages/19001949/1944/1944.100.83025.rev.width350.jpg],"from":10,"to":38,"title":"Bronze Coin, Ecbatana, AD 10 - AD 38. 1944.100.83025"}{"image_urls":[http://numismatics.org/collectionimages/19001949/1948/1948.4.132.rev.width350.jpg],"from":10,"to":38,"title":"Bronze Coin, Ecbatana, AD 10 - AD 38. 1948.4.132"}{"image_urls":[http://numismatics.org/collectionimages/19001949/1944/1944.100.83037.rev.width350.jpg],"from":10,"to":38,"title":"Bronze Coin, Ecbatana, AD 10 - AD 38. 1944.100.83037"}{"image_urls":[http://numismatics.org/collectionimages/19001949/1944/1944.100.83115.rev.width350.jpg],"from":10,"to":38,"title":"Silver Drachm, Ecbatana, AD 10 - AD 38. 1944.100.83115"}{"image_urls":[http://numismatics.org/collectionimages/19001949/1944/1944.100.83084.rev.width350.jpg],"from":10,"to":38,"title":"Silver Drachm, Ecbatana, AD 10 - AD 38. 1944.100.83084"}{"image_urls":[http://numismatics.org/collectionimages/19001949/1944/1944.100.83078.rev.width350.jpg],"from":10,"to":38,"title":"Bronze Coin, Ecbatana, AD 10 - AD 38. 1944.100.83078"}{"image_urls":[http://numismatics.org/collectionimages/19501999/1973/1973.56.1665.rev.width350.jpg],"from":10,"to":38,"title":"Bronze Coin, Ecbatana, AD 10 - AD 38. 1973.56.1665"}{"image_urls":[http://numismatics.org/collectionimages/19501999/1973/1973.56.1659.rev.width350.jpg],"from":10,"to":38,"title":"Silver Drachm, Ecbatana, AD 10 - AD 38. 1973.56.1659"}{"image_urls":[http://numismatics.org/collectionimages/19001949/1944/1944.100.83072.rev.width350.jpg],"from":10,"to":38,"title":"Silver Drachm, Ecbatana, AD 10 - AD 38. 1944.100.83072"}{"image_urls":[http://numismatics.org/collectionimages/19001949/1944/1944.100.83074.rev.width350.jpg],"from":10,"to":38,"title":"Bronze Coin, Ecbatana, AD 10 - AD 38. 1944.100.83074"}{"image_urls":[http://numismatics.org/collectionimages/19001949/1944/1944.100.83009.rev.width350.jpg],"from":10,"to":38,"title":"Silver Tetradrachm, Seleuceia ad Tigrim, AD 10 - AD 38. 1944.100.83009"}{"image_urls":[http://numismatics.org/collectionimages/19501999/1991/1991.3.59.rev.width350.jpg],"from":10,"to":38,"title":"Bronze Dichalkous, Ecbatana, AD 10 - AD 38. 1991.3.59"}{"image_urls":[http://numismatics.org/collectionimages/19001949/1908/1908.115.19.rev.width350.jpg],"from":10,"to":38,"title":"Silver Drachm, Ecbatana, AD 10 - AD 38. 1908.115.19"}{"image_urls":[http://numismatics.org/collectionimages/19001949/1944/1944.100.83069.rev.width350.jpg],"from":10,"to":38,"title":"Silver Drachm, Ecbatana, AD 10 - AD 38. 1944.100.83069"}{"image_urls":[https://finds.org.uk/images/jwatters/Roman%20coin%2006%2049%20-%202.jpg],"from":2,"to":14,"title":"BH-F72437: A coin issued by Augustus"}{"image_urls":[http://numismatics.org/collectionimages/20002049/2008/2008.24.10.rev.width350.jpg],"from":4,"to":14,"title":"Bronze dupondius of Tiberius, Leptis Minor, AD 4 - AD 14. 2008.24.10"}{"image_urls":[https://finds.org.uk/images/dwilliams/05.374a.jpg],"from":7,"to":337,"title":"SUR-346EC1: A coin issued by Constantine I"}{"image_urls":[https://finds.org.uk/images/smokedkelpie/KENT-8EBD41.jpg],"from":8,"to":41,"title":"KENT-8EBD41: A coin issued by Cunobelin"}{"image_urls":[https://finds.org.uk/images/margaretb/14-667.JPG],"from":8,"to":41,"title":"SUR-40AF76: A coin issued by Cunobelin"}{"image_urls":[https://finds.org.uk/images/eeh7/KENT-DD23D0.jpg],"from":8,"to":41,"title":"KENT-DD23D0: A coin issued by Cunobelin"}{"image_urls":[https://finds.org.uk/images/abyard/OXPAS2015182.jpg],"from":8,"to":41,"title":"BERK-EFC8C1: A coin issued by Cunobelin"}{"image_urls":[https://finds.org.uk/images/kmarsden/ESS-B58210.JPG],"from":8,"to":41,"title":"ESS-B58210: A coin issued by Cunobelin"}{"image_urls":[https://finds.org.uk/images/maritime/296.%20Gold%20Iron%20Age%20Cunobelin%20coin%20Y296.jpg],"from":8,"to":41,"title":"BERK-E511E7: A coin issued by Cunobelin"}{"image_urls":[https://finds.org.uk/images/abyard/20148445.jpg],"from":8,"to":41,"title":"BERK-83C7AF: A coin issued by Cunobelin"}{"image_urls":[http://numismatics.org/collectionimages/19001949/1944/1944.100.39257.rev.width350.jpg],"from":8,"to":10,"title":"RIC I (second edition) Augustus 236B. 1944.100.39257"}{"image_urls":[http://numismatics.org/collectionimages/19001949/1944/1944.100.83001.rev.width350.jpg],"from":8,"to":12,"title":"Silver Drachm, Ecbatana, AD 8 - AD 12. 1944.100.83001"}{"image_urls":[http://numismatics.org/collectionimages/19501999/1973/1973.56.1652.rev.width350.jpg],"from":8,"to":12,"title":"Silver Drachm, Ecbatana, AD 8 - AD 12. 1973.56.1652"}{"image_urls":[http://numismatics.org/collectionimages/19001949/1944/1944.100.83000.rev.width350.jpg],"from":8,"to":12,"title":"Silver Drachm, Ecbatana, AD 8 - AD 12. 1944.100.83000"}{"image_urls":[http://numismatics.org/collectionimages/19001949/1944/1944.100.83007.rev.width350.jpg],"from":8,"to":12,"title":"Bronze Coin, Ecbatana, AD 8 - AD 12. 1944.100.83007"}{"image_urls":[http://numismatics.org/collectionimages/19001949/1944/1944.100.83006.rev.width350.jpg],"from":8,"to":12,"title":"Bronze Coin, Ecbatana, AD 8 - AD 12. 1944.100.83006"}{"image_urls":[http://numismatics.org/collectionimages/00001899/0000/0000.999.52971.rev.width350.jpg],"from":8,"to":12,"title":"Silver Drachm, Ecbatana, AD 8 - AD 12. 0000.999.52971"}{"image_urls":[http://numismatics.org/collectionimages/19001949/1944/1944.100.83002.rev.width350.jpg],"from":8,"to":12,"title":"Silver Drachm, Ecbatana, AD 8 - AD 12. 1944.100.83002"}{"image_urls":[http://numismatics.org/collectionimages/19001949/1944/1944.100.39256.rev.width350.jpg],"from":8,"to":10,"title":"RIC I (second edition) Augustus 236A. 1944.100.39256"}{"image_urls":[http://numismatics.org/collectionimages/19001949/1944/1944.100.83005.rev.width350.jpg],"from":8,"to":12,"title":"Bronze Coin, Ecbatana, AD 8 - AD 12. 1944.100.83005"}{"image_urls":[http://numismatics.org/collectionimages/19501999/1959/1959.106.13.rev.width350.jpg],"from":8,"to":12,"title":"Bronze Coin, Ecbatana, AD 8 - AD 12. 1959.106.13"}{"image_urls":[http://numismatics.org/collectionimages/19001949/1944/1944.100.83008.rev.width350.jpg],"from":8,"to":12,"title":"Bronze Coin, Ecbatana, AD 8 - AD 12. 1944.100.83008"}{"image_urls":[http://numismatics.org/collectionimages/19501999/1970/1970.156.729.rev.width350.jpg],"from":8,"to":12,"title":"Silver Drachm, Ecbatana, AD 8 - AD 12. 1970.156.729"}{"image_urls":[http://numismatics.org/collectionimages/19001949/1944/1944.100.83003.rev.width350.jpg],"from":8,"to":12,"title":"Silver Drachm, Ecbatana, AD 8 - AD 12. 1944.100.83003"}{"image_urls":[http://numismatics.org/collectionimages/19001949/1944/1944.100.39255.rev.width350.jpg],"from":8,"to":10,"title":"RIC I (second edition) Augustus 240. 1944.100.39255"}{"image_urls":[http://numismatics.org/collectionimages/19001949/1944/1944.100.83004.rev.width350.jpg],"from":8,"to":12,"title":"Bronze Coin, Ecbatana, AD 8 - AD 12. 1944.100.83004"}{"image_urls":[http://numismatics.org/collectionimages/00001899/0000/0000.999.16790.rev.width350.jpg],"from":8,"to":10,"title":"RIC I (second edition) Augustus 237. 0000.999.16790"}{"image_urls":[http://numismatics.org/collectionimages/19501999/1991/1991.3.55.rev.width350.jpg],"from":8,"to":12,"title":"Silver Drachm, Ecbatana, AD 8 - AD 12. 1991.3.55"}{"image_urls":[http://numismatics.org/collectionimages/19501999/1977/1977.158.795.rev.width350.jpg],"from":8,"to":12,"title":"Silver Drachm, Ecbatana, AD 8 - AD 12. 1977.158.795"}{"image_urls":[http://numismatics.org/collectionimages/19501999/1973/1973.56.1653.rev.width350.jpg],"from":8,"to":12,"title":"Bronze Coin, Ecbatana, AD 8 - AD 12. 1973.56.1653"}{"image_urls":[https://finds.org.uk/images/dwilliams/08.450.JPG],"from":9,"to":14,"title":"SUR-24BB47: A coin issued by Augustus"}{"image_urls":[https://finds.org.uk/images/fminter/SUT022SF-D03781.jpg],"from":9,"to":14,"title":"SF-D03781: A coin issued by Tiberius"}{"image_urls":[https://finds.org.uk/images/wenkedomscheit/2013.150.jpg],"from":9,"to":14,"title":"NMGW-97DFAA: A coin with an unrecorded\/uncertain issuer."}{"image_urls":[https://finds.org.uk/images/preavill/HESH-E68E74.jpg],"from":9,"to":14,"title":"HESH-E68E74: A coin issued by Tiberius"}{"image_urls":[http://numismatics.org/collectionimages/19001949/1944/1944.100.39131.rev.width350.jpg],"from":9,"to":14,"title":"RIC I (second edition) Augustus 231A. 1944.100.39131"}{"image_urls":[http://numismatics.org/collectionimages/19501999/1984/1984.176.3.rev.width350.jpg],"from":9,"to":14,"title":"RIC I (second edition) Augustus 233. 1984.176.3"}{"image_urls":[http://numismatics.org/collectionimages/19001949/1944/1944.100.39130.rev.width350.jpg],"from":9,"to":14,"title":"RIC I (second edition) Augustus 231A. 1944.100.39130"}{"image_urls":[http://numismatics.org/collectionimages/19001949/1944/1944.100.39133.rev.width350.jpg],"from":9,"to":14,"title":"RIC I (second edition) Augustus 234. 1944.100.39133"}{"image_urls":[http://numismatics.org/collectionimages/19001949/1944/1944.100.39132.rev.width350.jpg],"from":9,"to":14,"title":"RIC I (second edition) Augustus 233. 1944.100.39132"}{"image_urls":[http://numismatics.org/collectionimages/00001899/0000/0000.999.16781.rev.width350.jpg],"from":9,"to":14,"title":"RIC I (second edition) Augustus 231A. 0000.999.16781"}