{"image_urls":[https://finds.org.uk/images/wscott/135137%20.JPG],"from":1030,"to":1042,"title":"LEIC-135137: A coin with an unrecorded\/uncertain issuer."}{"image_urls":[http://numismatics.org/collectionimages/19001949/1946/1946.51.102.rev.width350.jpg],"from":1034,"to":1041,"title":"Gold Histamenon of Michael IV, Constantinople, 1034 - 1041. 1946.51.102"}{"image_urls":[http://numismatics.org/collectionimages/19501999/1980/1980.109.300.rev.width350.jpg],"from":1034,"to":1041,"title":"Gold Histamenon of Michael IV, Constantinople, 1034 - 1041. 1980.109.300"}{"image_urls":[http://numismatics.org/collectionimages/19501999/1977/1977.158.1179.rev.width350.jpg],"from":1034,"to":1041,"title":"Gold Histamenon of Michael IV, Constantinople, 1034 - 1041. 1977.158.1179"}{"image_urls":[http://numismatics.org/collectionimages/19001949/1948/1948.19.499.rev.width350.jpg],"from":1034,"to":1041,"title":"Gold Histamenon of Michael IV, Thessalonica, 1034 - 1041. 1948.19.499"}{"image_urls":[http://numismatics.org/collectionimages/19501999/1968/1968.131.320.rev.width350.jpg],"from":1034,"to":1041,"title":"Gold Histamenon of Michael IV, Thessalonica, 1034 - 1041. 1968.131.320"}{"image_urls":[http://numismatics.org/collectionimages/19001949/1946/1946.51.101.rev.width350.jpg],"from":1034,"to":1041,"title":"Gold Histamenon of Michael IV, Constantinople, 1034 - 1041. 1946.51.101"}{"image_urls":[http://numismatics.org/collectionimages/19501999/1968/1968.131.319.rev.width350.jpg],"from":1034,"to":1041,"title":"Gold Histamenon of Michael IV, Constantinople, 1034 - 1041. 1968.131.319"}{"image_urls":[http://numismatics.org/collectionimages/19501999/1977/1977.158.1178.rev.width350.jpg],"from":1034,"to":1041,"title":"Gold Histamenon of Michael IV, Constantinople, 1034 - 1041. 1977.158.1178"}{"image_urls":[https://finds.org.uk/images/abrown/LVM_SF-FCACC9.jpg],"from":1035,"to":1040,"title":"SF-FCACC9: A coin issued by Harold Harefoot"}{"image_urls":[https://finds.org.uk/images/stephaniesmith/SUSS-F224B6.jpg],"from":1036,"to":1038,"title":"SUSS-F224B6: A coin issued by Harold Harefoot"}{"image_urls":[https://finds.org.uk/images/dpennock/399%20Harold%20I%20Penny%20Obv.JPG],"from":1038,"to":1040,"title":"KENT-4F14E1: A coin issued by Harold Harefoot"}{"image_urls":[https://finds.org.uk/images/lburnett/SUSS-2E6268.JPG],"from":260,"to":1268,"title":"SUSS-2E6268: A coin issued by Gallienus (sole reign)"}{"image_urls":[https://finds.org.uk/images/ksutton/Skuce%20-%20Roman%20perforated%20coin%20-%20june%2006.jpg],"from":321,"to":1066,"title":"BERK-232092: A coin issued by Licinius I"}{"image_urls":[https://finds.org.uk/images/adaubney/LIN9795.jpg],"from":326,"to":1700,"title":"LIN-10A2D7: A coin issued by Constantine I"}