[{"image_urls":["https:\/\/finds.org.uk\/images\/cjohnson\/WMID-083531.JPG"],"from":336,"to":337,"title":"WMID-083531: A coin issued by Constantine I"},{"image_urls":["https:\/\/finds.org.uk\/images\/jwatters\/Roman%20coin%2004%20150%20-%2017%20all.jpg"],"from":336,"to":342,"title":"BH-BCEAE7: A coin issued by Helena"},{"image_urls":["https:\/\/finds.org.uk\/images\/vdrost\/BM095109obv.JPG"],"from":336,"to":336,"title":"BM-095109: A coin issued by House of Constantine"},{"image_urls":["https:\/\/finds.org.uk\/images\/hfowler\/CAM-E8A8E3.jpg"],"from":336,"to":340,"title":"CAM-E8A8E3: A coin issued by House of Constantine"},{"image_urls":["https:\/\/finds.org.uk\/images\/fbasford\/IOW2012-7-1.JPG"],"from":336,"to":340,"title":"IOW-5B9EF2: A coin issued by House of Constantine"},{"image_urls":["https:\/\/finds.org.uk\/images\/alav\/avk%20%2819%29.jpg"],"from":336,"to":341,"title":"PUBLIC-23FDB8: A coin issued by House of Constantine"},{"image_urls":["https:\/\/finds.org.uk\/images\/awillis\/LIN-957524.jpg"],"from":336,"to":340,"title":"LIN-957524: A coin issued by Constantine I"},{"image_urls":["https:\/\/finds.org.uk\/images\/annab\/coin%202.jpg"],"from":336,"to":336,"title":"SOM-64FEF2: A coin issued by House of Constantine"},{"image_urls":["https:\/\/finds.org.uk\/images\/alav\/aqa%20%281%29.jpg"],"from":336,"to":340,"title":"PUBLIC-1D7FE5: A coin issued by Constantius II"},{"image_urls":["https:\/\/finds.org.uk\/images\/fbasford\/IOW2012-4-278.JPG"],"from":336,"to":337,"title":"IOW-987E72: A coin issued by Constantine I"},{"image_urls":["https:\/\/finds.org.uk\/images\/yorkvol\/BR1014.jpg"],"from":336,"to":337,"title":"YORYM-7D7F54: A coin issued by House of Constantine"},{"image_urls":["https:\/\/finds.org.uk\/images\/pwalton\/3AF715.jpg"],"from":336,"to":336,"title":"NCL-3AF715: A coin issued by House of Constantine"},{"image_urls":["https:\/\/finds.org.uk\/images\/rhenry2\/WILT-485AB2.jpg"],"from":336,"to":336,"title":"WILT-485AB2: A coin issued by Dalmatius"},{"image_urls":["https:\/\/finds.org.uk\/images\/dwilliams\/06.1184.JPG"],"from":336,"to":337,"title":"SUR-DFB4C1: A coin issued by Dalmatius"},{"image_urls":["https:\/\/finds.org.uk\/images\/atyacke\/mixt%20030.jpg"],"from":336,"to":337,"title":"CORN-E743D6: A coin issued by Constantine I"},{"image_urls":["https:\/\/finds.org.uk\/images\/vdrost\/DSC02082.JPG"],"from":336,"to":336,"title":"BM-4D7552: A coin issued by House of Constantine"},{"image_urls":["https:\/\/finds.org.uk\/images\/harrymetsally1992\/Roman1.jpg"],"from":336,"to":336,"title":"PUBLIC-E2A1C5: A coin issued by Constantius II"},{"image_urls":["https:\/\/finds.org.uk\/images\/wscott\/ACCA51.JPG"],"from":336,"to":336,"title":"LEIC-ACCA51: A coin issued by Constans"},{"image_urls":["https:\/\/finds.org.uk\/images\/fbasford\/IOW2013-1-191.JPG"],"from":336,"to":340,"title":"IOW-6A3285: A coin issued by House of Constantine"},{"image_urls":["https:\/\/finds.org.uk\/images\/jwatters\/Roman_coin_15_92_9.jpg"],"from":336,"to":336,"title":"BH-9738D9: A coin issued by Constantine I"},{"image_urls":["https:\/\/finds.org.uk\/images\/jwatters\/Roman%20coin%2004%20150%20-%2010%20all.jpg"],"from":336,"to":342,"title":"BH-6D9180: A coin issued by Theodora"},{"image_urls":["https:\/\/finds.org.uk\/images\/abyard\/Rawlins%20158.jpg"],"from":336,"to":336,"title":"BERK-7206C1: A coin issued by Constantine II"},{"image_urls":["https:\/\/finds.org.uk\/images\/law\/MH0002.jpg"],"from":336,"to":337,"title":"YORYM-C8E677: A coin issued by House of Constantine"},{"image_urls":["https:\/\/finds.org.uk\/images\/tgilmore\/WMID-A77CD6.jpg"],"from":336,"to":337,"title":"WMID-A77CD6: A coin issued by Constantine I"},{"image_urls":["https:\/\/finds.org.uk\/images\/rwebley\/HAMP-EF8DF0CIInummusGE1.jpg"],"from":336,"to":336,"title":"HAMP-EF8DF0: A coin issued by Constantine II"},{"image_urls":["https:\/\/finds.org.uk\/images\/jwatters\/Roman%20coin%2004%20196%20-%2061%20all.jpg"],"from":336,"to":342,"title":"BH-AB3404: A coin issued by Helena"},{"image_urls":["https:\/\/finds.org.uk\/images\/mforeman\/NLM28888.jpg"],"from":336,"to":340,"title":"NLM-588B01: A coin issued by Constans"},{"image_urls":["https:\/\/finds.org.uk\/images\/tcrnlje\/SUSS-B090E3numCII.jpg"],"from":336,"to":337,"title":"SUSS-B090E3: A coin issued by Constantine II"},{"image_urls":["https:\/\/finds.org.uk\/images\/fbasford\/IOW2013-2-355.JPG"],"from":336,"to":336,"title":"IOW-221D55: A coin issued by Dalmatius"},{"image_urls":["https:\/\/finds.org.uk\/images\/abrown\/BRG_SF-108988.jpg"],"from":336,"to":337,"title":"SF-108988: A coin issued by Constans"},{"image_urls":["https:\/\/finds.org.uk\/images\/cmcdonald\/Brown%202s1s.jpg"],"from":336,"to":337,"title":"ESS-C4FC76: A coin issued by Constantine I"},{"image_urls":["http:\/\/numismatics.org\/collectionimages\/20002049\/2011\/2011.21.546.rev.width350.jpg"],"from":336,"to":400,"title":"drachm, Larissa, AD 400 - AD 336. 2011.21.546"},{"image_urls":["http:\/\/numismatics.org\/collectionimages\/19001949\/1944\/1944.100.13323.rev.width350.jpg"],"from":336,"to":337,"title":"Silver Medallion, Treveri, AD 336 - AD 337. 1944.100.13323"},{"image_urls":["https:\/\/finds.org.uk\/images\/dwilliams\/05.374a.jpg"],"from":7,"to":337,"title":"SUR-346EC1: A coin issued by Constantine I"}]