[{"image_urls":["https:\/\/finds.org.uk\/images\/jwatters\/Roman%20coin%200434%20%282%29%20-%207%20obv.jpg"],"from":349,"to":354,"title":"BH-4ACB57: A coin issued by Magnentius"},{"image_urls":["https:\/\/finds.org.uk\/images\/jwatters\/Roman%20coin%2004-11%203%20all.jpg"],"from":349,"to":354,"title":"BH-9AB577: A coin issued by Magnentius"},{"image_urls":["https:\/\/finds.org.uk\/images\/smokedkelpie\/Roman%20coin.jpg"],"from":43,"to":410,"title":"KENT-BA9AB2: A coin issued by Constantius II"}]